<?xml version="1.0" encoding="UTF-8"?>
<kit
	firmwareVersion="c1.1.0"
	earliestCompatibleFirmware="4.1.0-alpha"
	lpfMode="24dB"
	hpfMode="HPLadder"
	modFXType="none"
	filterRoute="H2L"
	modFXCurrentParam="feedback"
	currentFilterType="lpf">
	<delay
		pingPong="1"
		analog="0"
		syncType="0"
		syncLevel="7" />
	<sidechain
		syncType="0"
		syncLevel="6"
		attack="327244"
		release="936" />
	<audioCompressor
		attack="83886080"
		release="83886080"
		thresh="0"
		ratio="1073741824"
		compHPF="0" />
	<defaultParams
		reverbAmount="0x80000000"
		volume="0x00000000"
		pan="0x00000000"
		sidechainCompressorShape="0xDC28F5B2"
		modFXDepth="0x00000000"
		modFXRate="0xE0000000"
		stutterRate="0x00000000"
		sampleRateReduction="0x80000000"
		bitCrush="0x80000000"
		modFXOffset="0x00000000"
		modFXFeedback="0x80000000"
		compressorThreshold="0x00000000">
		<delay
			rate="0x00000000"
			feedback="0x80000000" />
		<lpf
			frequency="0x7FFFFFFF"
			resonance="0x80000000" />
		<hpf
			frequency="0x80000000"
			resonance="0x80000000" />
		<equalizer
			bass="0x00000000"
			treble="0x00000000"
			bassFrequency="0x00000000"
			trebleFrequency="0x00000000" />
	</defaultParams>
	<soundSources>
		<sound
			name="01-kick"
			path=""
			polyphonic="auto"
			voicePriority="1"
			mode="subtractive"
			lpfMode="24dB"
			hpfMode="HPLadder"
			modFXType="none"
			filterRoute="H2L">
			<osc1
				type="sample"
				loopMode="1"
				reversed="0"
				timeStretchEnable="0"
				timeStretchAmount="0"
				fileName="SAMPLES/op1kits/acoustic_toy/01-kick.wav">
				
			</osc1>
			<osc2
				type="sample"
				loopMode="0"
				reversed="0"
				timeStretchEnable="0"
				timeStretchAmount="0">
			</osc2>
			<lfo1 type="triangle" syncType="0" syncLevel="0" />
			<lfo2 type="triangle" />
			<unison num="1" detune="8" spread="0" />
			<delay
				pingPong="1"
				analog="0"
				syncType="0"
				syncLevel="7" />
			<sidechain
				syncType="0"
				syncLevel="6"
				attack="327244"
				release="936" />
			<audioCompressor
				attack="83886080"
				release="83886080"
				thresh="0"
				ratio="1073741824"
				compHPF="0" />
			<defaultParams
				arpeggiatorGate="0x00000000"
				ratchetProbability="0x80000000"
				ratchetAmount="0x80000000"
				sequenceLength="0x80000000"
				portamento="0x80000000"
				compressorShape="0xDC28F5B2"
				oscAVolume="0x7FFFFFFF"
				oscAPulseWidth="0x00000000"
				oscAWavetablePosition="0x00000000"
				oscBVolume="0x80000000"
				oscBPulseWidth="0x00000000"
				oscBWavetablePosition="0x00000000"
				noiseVolume="0x80000000"
				volume="0x4CCCCCA8"
				pan="0x00000000"
				waveFold="0x80000000"
				lpfFrequency="0x7FFFFFFF"
				lpfResonance="0x80000000"
				lpfMorph="0x80000000"
				hpfFrequency="0x80000000"
				hpfResonance="0x80000000"
				hpfMorph="0x80000000"
				lfo1Rate="0x1999997E"
				lfo2Rate="0x00000000"
				modulator1Amount="0x80000000"
				modulator1Feedback="0x80000000"
				modulator2Amount="0x80000000"
				modulator2Feedback="0x80000000"
				carrier1Feedback="0x80000000"
				carrier2Feedback="0x80000000"
				modFXRate="0x00000000"
				modFXDepth="0x00000000"
				delayRate="0x00000000"
				delayFeedback="0x80000000"
				reverbAmount="0x80000000"
				arpeggiatorRate="0x00000000"
				stutterRate="0x00000000"
				sampleRateReduction="0x80000000"
				bitCrush="0x80000000"
				modFXOffset="0x00000000"
				modFXFeedback="0x00000000"
				compressorThreshold="0x00000000">
				<envelope1
					attack="0x80000000"
					decay="0xE6666654"
					sustain="0x7FFFFFD2"
					release="0x80000000" />
				<envelope2
					attack="0xE6666654"
					decay="0xE6666654"
					sustain="0xFFFFFFE9"
					release="0xE6666654" />
				<patchCables>
					<patchCable
						source="velocity"
						destination="volume"
						amount="0x3FFFFFE8" />
					<patchCable
						source="aftertouch"
						destination="volume"
						amount="0x2A3D7094" />
					<patchCable
						source="y"
						destination="lpfFrequency"
						amount="0x19999990" />
				</patchCables>
				<equalizer
					bass="0x00000000"
					treble="0x00000000"
					bassFrequency="0x00000000"
					trebleFrequency="0x00000000" />
			</defaultParams>
			<arpeggiator
				arpMode="off"
				noteMode="up"
				octaveMode="up"
				mpeVelocity="off"
				numOctaves="2"
				rhythm="0"
				syncType="0"
				syncLevel="7" />
			<modKnobs>
				<modKnob controlsParam="pan" />
				<modKnob controlsParam="volumePostFX" />
				<modKnob controlsParam="lpfResonance" />
				<modKnob controlsParam="lpfFrequency" />
				<modKnob controlsParam="env1Release" />
				<modKnob controlsParam="env1Attack" />
				<modKnob controlsParam="delayFeedback" />
				<modKnob controlsParam="delayRate" />
				<modKnob controlsParam="reverbAmount" />
				<modKnob controlsParam="volumePostReverbSend" patchAmountFromSource="compressor" />
				<modKnob controlsParam="pitch" patchAmountFromSource="lfo1" />
				<modKnob controlsParam="lfo1Rate" />
				<modKnob controlsParam="pitch" />
				<modKnob controlsParam="stutterRate" />
				<modKnob controlsParam="bitcrushAmount" />
				<modKnob controlsParam="sampleRateReduction" />
			</modKnobs>
		</sound>
		<sound
			name="02-kick_alt"
			path=""
			polyphonic="auto"
			voicePriority="1"
			mode="subtractive"
			lpfMode="24dB"
			hpfMode="HPLadder"
			modFXType="none"
			filterRoute="H2L">
			<osc1
				type="sample"
				loopMode="1"
				reversed="0"
				timeStretchEnable="0"
				timeStretchAmount="0"
				fileName="SAMPLES/op1kits/acoustic_toy/02-kick_alt.wav">
				<zone
					startSamplePos="0"
					endSamplePos="7034" />
			</osc1>
			<osc2
				type="sample"
				loopMode="0"
				reversed="0"
				timeStretchEnable="0"
				timeStretchAmount="0">
			</osc2>
			<lfo1 type="triangle" syncType="0" syncLevel="0" />
			<lfo2 type="triangle" />
			<unison num="1" detune="8" spread="0" />
			<delay
				pingPong="1"
				analog="0"
				syncType="0"
				syncLevel="7" />
			<sidechain
				syncType="0"
				syncLevel="6"
				attack="327244"
				release="936" />
			<audioCompressor
				attack="83886080"
				release="83886080"
				thresh="0"
				ratio="1073741824"
				compHPF="0" />
			<defaultParams
				arpeggiatorGate="0x00000000"
				ratchetProbability="0x80000000"
				ratchetAmount="0x80000000"
				sequenceLength="0x80000000"
				portamento="0x80000000"
				compressorShape="0xDC28F5B2"
				oscAVolume="0x7FFFFFFF"
				oscAPulseWidth="0x00000000"
				oscAWavetablePosition="0x00000000"
				oscBVolume="0x80000000"
				oscBPulseWidth="0x00000000"
				oscBWavetablePosition="0x00000000"
				noiseVolume="0x80000000"
				volume="0x4CCCCCA8"
				pan="0x00000000"
				waveFold="0x80000000"
				lpfFrequency="0x7FFFFFFF"
				lpfResonance="0x80000000"
				lpfMorph="0x80000000"
				hpfFrequency="0x80000000"
				hpfResonance="0x80000000"
				hpfMorph="0x80000000"
				lfo1Rate="0x1999997E"
				lfo2Rate="0x00000000"
				modulator1Amount="0x80000000"
				modulator1Feedback="0x80000000"
				modulator2Amount="0x80000000"
				modulator2Feedback="0x80000000"
				carrier1Feedback="0x80000000"
				carrier2Feedback="0x80000000"
				modFXRate="0x00000000"
				modFXDepth="0x00000000"
				delayRate="0x00000000"
				delayFeedback="0x80000000"
				reverbAmount="0x80000000"
				arpeggiatorRate="0x00000000"
				stutterRate="0x00000000"
				sampleRateReduction="0x80000000"
				bitCrush="0x80000000"
				modFXOffset="0x00000000"
				modFXFeedback="0x00000000"
				compressorThreshold="0x00000000">
				<envelope1
					attack="0x80000000"
					decay="0xE6666654"
					sustain="0x7FFFFFD2"
					release="0x80000000" />
				<envelope2
					attack="0xE6666654"
					decay="0xE6666654"
					sustain="0xFFFFFFE9"
					release="0xE6666654" />
				<patchCables>
					<patchCable
						source="velocity"
						destination="volume"
						amount="0x3FFFFFE8" />
					<patchCable
						source="aftertouch"
						destination="volume"
						amount="0x2A3D7094" />
					<patchCable
						source="y"
						destination="lpfFrequency"
						amount="0x19999990" />
				</patchCables>
				<equalizer
					bass="0x00000000"
					treble="0x00000000"
					bassFrequency="0x00000000"
					trebleFrequency="0x00000000" />
			</defaultParams>
			<arpeggiator
				arpMode="off"
				noteMode="up"
				octaveMode="up"
				mpeVelocity="off"
				numOctaves="2"
				rhythm="0"
				syncType="0"
				syncLevel="7" />
			<modKnobs>
				<modKnob controlsParam="pan" />
				<modKnob controlsParam="volumePostFX" />
				<modKnob controlsParam="lpfResonance" />
				<modKnob controlsParam="lpfFrequency" />
				<modKnob controlsParam="env1Release" />
				<modKnob controlsParam="env1Attack" />
				<modKnob controlsParam="delayFeedback" />
				<modKnob controlsParam="delayRate" />
				<modKnob controlsParam="reverbAmount" />
				<modKnob controlsParam="volumePostReverbSend" patchAmountFromSource="compressor" />
				<modKnob controlsParam="pitch" patchAmountFromSource="lfo1" />
				<modKnob controlsParam="lfo1Rate" />
				<modKnob controlsParam="pitch" />
				<modKnob controlsParam="stutterRate" />
				<modKnob controlsParam="bitcrushAmount" />
				<modKnob controlsParam="sampleRateReduction" />
			</modKnobs>
		</sound>
		<sound
			name="03-snare"
			path=""
			polyphonic="auto"
			voicePriority="1"
			mode="subtractive"
			lpfMode="24dB"
			hpfMode="HPLadder"
			modFXType="none"
			filterRoute="H2L">
			<osc1
				type="sample"
				loopMode="1"
				reversed="0"
				timeStretchEnable="0"
				timeStretchAmount="0"
				fileName="SAMPLES/op1kits/acoustic_toy/03-snare.wav">
				<zone
					startSamplePos="0"
					endSamplePos="14005" />
			</osc1>
			<osc2
				type="sample"
				loopMode="0"
				reversed="0"
				timeStretchEnable="0"
				timeStretchAmount="0">
			</osc2>
			<lfo1 type="triangle" syncType="0" syncLevel="0" />
			<lfo2 type="triangle" />
			<unison num="1" detune="8" spread="0" />
			<delay
				pingPong="1"
				analog="0"
				syncType="0"
				syncLevel="7" />
			<sidechain
				syncType="0"
				syncLevel="6"
				attack="327244"
				release="936" />
			<audioCompressor
				attack="83886080"
				release="83886080"
				thresh="0"
				ratio="1073741824"
				compHPF="0" />
			<defaultParams
				arpeggiatorGate="0x00000000"
				ratchetProbability="0x80000000"
				ratchetAmount="0x80000000"
				sequenceLength="0x80000000"
				portamento="0x80000000"
				compressorShape="0xDC28F5B2"
				oscAVolume="0x7FFFFFFF"
				oscAPulseWidth="0x00000000"
				oscAWavetablePosition="0x00000000"
				oscBVolume="0x80000000"
				oscBPulseWidth="0x00000000"
				oscBWavetablePosition="0x00000000"
				noiseVolume="0x80000000"
				volume="0x4CCCCCA8"
				pan="0x00000000"
				waveFold="0x80000000"
				lpfFrequency="0x7FFFFFFF"
				lpfResonance="0x80000000"
				lpfMorph="0x80000000"
				hpfFrequency="0x80000000"
				hpfResonance="0x80000000"
				hpfMorph="0x80000000"
				lfo1Rate="0x1999997E"
				lfo2Rate="0x00000000"
				modulator1Amount="0x80000000"
				modulator1Feedback="0x80000000"
				modulator2Amount="0x80000000"
				modulator2Feedback="0x80000000"
				carrier1Feedback="0x80000000"
				carrier2Feedback="0x80000000"
				modFXRate="0x00000000"
				modFXDepth="0x00000000"
				delayRate="0x00000000"
				delayFeedback="0x80000000"
				reverbAmount="0x80000000"
				arpeggiatorRate="0x00000000"
				stutterRate="0x00000000"
				sampleRateReduction="0x80000000"
				bitCrush="0x80000000"
				modFXOffset="0x00000000"
				modFXFeedback="0x00000000"
				compressorThreshold="0x00000000">
				<envelope1
					attack="0x80000000"
					decay="0xE6666654"
					sustain="0x7FFFFFD2"
					release="0x80000000" />
				<envelope2
					attack="0xE6666654"
					decay="0xE6666654"
					sustain="0xFFFFFFE9"
					release="0xE6666654" />
				<patchCables>
					<patchCable
						source="velocity"
						destination="volume"
						amount="0x3FFFFFE8" />
					<patchCable
						source="aftertouch"
						destination="volume"
						amount="0x2A3D7094" />
					<patchCable
						source="y"
						destination="lpfFrequency"
						amount="0x19999990" />
				</patchCables>
				<equalizer
					bass="0x00000000"
					treble="0x00000000"
					bassFrequency="0x00000000"
					trebleFrequency="0x00000000" />
			</defaultParams>
			<arpeggiator
				arpMode="off"
				noteMode="up"
				octaveMode="up"
				mpeVelocity="off"
				numOctaves="2"
				rhythm="0"
				syncType="0"
				syncLevel="7" />
			<modKnobs>
				<modKnob controlsParam="pan" />
				<modKnob controlsParam="volumePostFX" />
				<modKnob controlsParam="lpfResonance" />
				<modKnob controlsParam="lpfFrequency" />
				<modKnob controlsParam="env1Release" />
				<modKnob controlsParam="env1Attack" />
				<modKnob controlsParam="delayFeedback" />
				<modKnob controlsParam="delayRate" />
				<modKnob controlsParam="reverbAmount" />
				<modKnob controlsParam="volumePostReverbSend" patchAmountFromSource="compressor" />
				<modKnob controlsParam="pitch" patchAmountFromSource="lfo1" />
				<modKnob controlsParam="lfo1Rate" />
				<modKnob controlsParam="pitch" />
				<modKnob controlsParam="stutterRate" />
				<modKnob controlsParam="bitcrushAmount" />
				<modKnob controlsParam="sampleRateReduction" />
			</modKnobs>
		</sound>
		<sound
			name="04-snare_alt"
			path=""
			polyphonic="auto"
			voicePriority="1"
			mode="subtractive"
			lpfMode="24dB"
			hpfMode="HPLadder"
			modFXType="none"
			filterRoute="H2L">
			<osc1
				type="sample"
				loopMode="1"
				reversed="0"
				timeStretchEnable="0"
				timeStretchAmount="0"
				fileName="SAMPLES/op1kits/acoustic_toy/04-snare_alt.wav">
				<zone
					startSamplePos="0"
					endSamplePos="38415" />
			</osc1>
			<osc2
				type="sample"
				loopMode="0"
				reversed="0"
				timeStretchEnable="0"
				timeStretchAmount="0">
			</osc2>
			<lfo1 type="triangle" syncType="0" syncLevel="0" />
			<lfo2 type="triangle" />
			<unison num="1" detune="8" spread="0" />
			<delay
				pingPong="1"
				analog="0"
				syncType="0"
				syncLevel="7" />
			<sidechain
				syncType="0"
				syncLevel="6"
				attack="327244"
				release="936" />
			<audioCompressor
				attack="83886080"
				release="83886080"
				thresh="0"
				ratio="1073741824"
				compHPF="0" />
			<defaultParams
				arpeggiatorGate="0x00000000"
				ratchetProbability="0x80000000"
				ratchetAmount="0x80000000"
				sequenceLength="0x80000000"
				portamento="0x80000000"
				compressorShape="0xDC28F5B2"
				oscAVolume="0x7FFFFFFF"
				oscAPulseWidth="0x00000000"
				oscAWavetablePosition="0x00000000"
				oscBVolume="0x80000000"
				oscBPulseWidth="0x00000000"
				oscBWavetablePosition="0x00000000"
				noiseVolume="0x80000000"
				volume="0x4CCCCCA8"
				pan="0x00000000"
				waveFold="0x80000000"
				lpfFrequency="0x7FFFFFFF"
				lpfResonance="0x80000000"
				lpfMorph="0x80000000"
				hpfFrequency="0x80000000"
				hpfResonance="0x80000000"
				hpfMorph="0x80000000"
				lfo1Rate="0x1999997E"
				lfo2Rate="0x00000000"
				modulator1Amount="0x80000000"
				modulator1Feedback="0x80000000"
				modulator2Amount="0x80000000"
				modulator2Feedback="0x80000000"
				carrier1Feedback="0x80000000"
				carrier2Feedback="0x80000000"
				modFXRate="0x00000000"
				modFXDepth="0x00000000"
				delayRate="0x00000000"
				delayFeedback="0x80000000"
				reverbAmount="0x80000000"
				arpeggiatorRate="0x00000000"
				stutterRate="0x00000000"
				sampleRateReduction="0x80000000"
				bitCrush="0x80000000"
				modFXOffset="0x00000000"
				modFXFeedback="0x00000000"
				compressorThreshold="0x00000000">
				<envelope1
					attack="0x80000000"
					decay="0xE6666654"
					sustain="0x7FFFFFD2"
					release="0x80000000" />
				<envelope2
					attack="0xE6666654"
					decay="0xE6666654"
					sustain="0xFFFFFFE9"
					release="0xE6666654" />
				<patchCables>
					<patchCable
						source="velocity"
						destination="volume"
						amount="0x3FFFFFE8" />
					<patchCable
						source="aftertouch"
						destination="volume"
						amount="0x2A3D7094" />
					<patchCable
						source="y"
						destination="lpfFrequency"
						amount="0x19999990" />
				</patchCables>
				<equalizer
					bass="0x00000000"
					treble="0x00000000"
					bassFrequency="0x00000000"
					trebleFrequency="0x00000000" />
			</defaultParams>
			<arpeggiator
				arpMode="off"
				noteMode="up"
				octaveMode="up"
				mpeVelocity="off"
				numOctaves="2"
				rhythm="0"
				syncType="0"
				syncLevel="7" />
			<modKnobs>
				<modKnob controlsParam="pan" />
				<modKnob controlsParam="volumePostFX" />
				<modKnob controlsParam="lpfResonance" />
				<modKnob controlsParam="lpfFrequency" />
				<modKnob controlsParam="env1Release" />
				<modKnob controlsParam="env1Attack" />
				<modKnob controlsParam="delayFeedback" />
				<modKnob controlsParam="delayRate" />
				<modKnob controlsParam="reverbAmount" />
				<modKnob controlsParam="volumePostReverbSend" patchAmountFromSource="compressor" />
				<modKnob controlsParam="pitch" patchAmountFromSource="lfo1" />
				<modKnob controlsParam="lfo1Rate" />
				<modKnob controlsParam="pitch" />
				<modKnob controlsParam="stutterRate" />
				<modKnob controlsParam="bitcrushAmount" />
				<modKnob controlsParam="sampleRateReduction" />
			</modKnobs>
		</sound>
		<sound
			name="05-rimshot"
			path=""
			polyphonic="auto"
			voicePriority="1"
			mode="subtractive"
			lpfMode="24dB"
			hpfMode="HPLadder"
			modFXType="none"
			filterRoute="H2L">
			<osc1
				type="sample"
				loopMode="1"
				reversed="0"
				timeStretchEnable="0"
				timeStretchAmount="0"
				fileName="SAMPLES/op1kits/acoustic_toy/05-rimshot.wav">
				<zone
					startSamplePos="0"
					endSamplePos="4170" />
			</osc1>
			<osc2
				type="sample"
				loopMode="0"
				reversed="0"
				timeStretchEnable="0"
				timeStretchAmount="0">
			</osc2>
			<lfo1 type="triangle" syncType="0" syncLevel="0" />
			<lfo2 type="triangle" />
			<unison num="1" detune="8" spread="0" />
			<delay
				pingPong="1"
				analog="0"
				syncType="0"
				syncLevel="7" />
			<sidechain
				syncType="0"
				syncLevel="6"
				attack="327244"
				release="936" />
			<audioCompressor
				attack="83886080"
				release="83886080"
				thresh="0"
				ratio="1073741824"
				compHPF="0" />
			<defaultParams
				arpeggiatorGate="0x00000000"
				ratchetProbability="0x80000000"
				ratchetAmount="0x80000000"
				sequenceLength="0x80000000"
				portamento="0x80000000"
				compressorShape="0xDC28F5B2"
				oscAVolume="0x7FFFFFFF"
				oscAPulseWidth="0x00000000"
				oscAWavetablePosition="0x00000000"
				oscBVolume="0x80000000"
				oscBPulseWidth="0x00000000"
				oscBWavetablePosition="0x00000000"
				noiseVolume="0x80000000"
				volume="0x4CCCCCA8"
				pan="0x00000000"
				waveFold="0x80000000"
				lpfFrequency="0x7FFFFFFF"
				lpfResonance="0x80000000"
				lpfMorph="0x80000000"
				hpfFrequency="0x80000000"
				hpfResonance="0x80000000"
				hpfMorph="0x80000000"
				lfo1Rate="0x1999997E"
				lfo2Rate="0x00000000"
				modulator1Amount="0x80000000"
				modulator1Feedback="0x80000000"
				modulator2Amount="0x80000000"
				modulator2Feedback="0x80000000"
				carrier1Feedback="0x80000000"
				carrier2Feedback="0x80000000"
				modFXRate="0x00000000"
				modFXDepth="0x00000000"
				delayRate="0x00000000"
				delayFeedback="0x80000000"
				reverbAmount="0x80000000"
				arpeggiatorRate="0x00000000"
				stutterRate="0x00000000"
				sampleRateReduction="0x80000000"
				bitCrush="0x80000000"
				modFXOffset="0x00000000"
				modFXFeedback="0x00000000"
				compressorThreshold="0x00000000">
				<envelope1
					attack="0x80000000"
					decay="0xE6666654"
					sustain="0x7FFFFFD2"
					release="0x80000000" />
				<envelope2
					attack="0xE6666654"
					decay="0xE6666654"
					sustain="0xFFFFFFE9"
					release="0xE6666654" />
				<patchCables>
					<patchCable
						source="velocity"
						destination="volume"
						amount="0x3FFFFFE8" />
					<patchCable
						source="aftertouch"
						destination="volume"
						amount="0x2A3D7094" />
					<patchCable
						source="y"
						destination="lpfFrequency"
						amount="0x19999990" />
				</patchCables>
				<equalizer
					bass="0x00000000"
					treble="0x00000000"
					bassFrequency="0x00000000"
					trebleFrequency="0x00000000" />
			</defaultParams>
			<arpeggiator
				arpMode="off"
				noteMode="up"
				octaveMode="up"
				mpeVelocity="off"
				numOctaves="2"
				rhythm="0"
				syncType="0"
				syncLevel="7" />
			<modKnobs>
				<modKnob controlsParam="pan" />
				<modKnob controlsParam="volumePostFX" />
				<modKnob controlsParam="lpfResonance" />
				<modKnob controlsParam="lpfFrequency" />
				<modKnob controlsParam="env1Release" />
				<modKnob controlsParam="env1Attack" />
				<modKnob controlsParam="delayFeedback" />
				<modKnob controlsParam="delayRate" />
				<modKnob controlsParam="reverbAmount" />
				<modKnob controlsParam="volumePostReverbSend" patchAmountFromSource="compressor" />
				<modKnob controlsParam="pitch" patchAmountFromSource="lfo1" />
				<modKnob controlsParam="lfo1Rate" />
				<modKnob controlsParam="pitch" />
				<modKnob controlsParam="stutterRate" />
				<modKnob controlsParam="bitcrushAmount" />
				<modKnob controlsParam="sampleRateReduction" />
			</modKnobs>
		</sound>
		<sound
			name="06-clapsnap"
			path=""
			polyphonic="auto"
			voicePriority="1"
			mode="subtractive"
			lpfMode="24dB"
			hpfMode="HPLadder"
			modFXType="none"
			filterRoute="H2L">
			<osc1
				type="sample"
				loopMode="1"
				reversed="0"
				timeStretchEnable="0"
				timeStretchAmount="0"
				fileName="SAMPLES/op1kits/acoustic_toy/06-clapsnap.wav">
				<zone
					startSamplePos="0"
					endSamplePos="7164" />
			</osc1>
			<osc2
				type="sample"
				loopMode="0"
				reversed="0"
				timeStretchEnable="0"
				timeStretchAmount="0">
			</osc2>
			<lfo1 type="triangle" syncType="0" syncLevel="0" />
			<lfo2 type="triangle" />
			<unison num="1" detune="8" spread="0" />
			<delay
				pingPong="1"
				analog="0"
				syncType="0"
				syncLevel="7" />
			<sidechain
				syncType="0"
				syncLevel="6"
				attack="327244"
				release="936" />
			<audioCompressor
				attack="83886080"
				release="83886080"
				thresh="0"
				ratio="1073741824"
				compHPF="0" />
			<defaultParams
				arpeggiatorGate="0x00000000"
				ratchetProbability="0x80000000"
				ratchetAmount="0x80000000"
				sequenceLength="0x80000000"
				portamento="0x80000000"
				compressorShape="0xDC28F5B2"
				oscAVolume="0x7FFFFFFF"
				oscAPulseWidth="0x00000000"
				oscAWavetablePosition="0x00000000"
				oscBVolume="0x80000000"
				oscBPulseWidth="0x00000000"
				oscBWavetablePosition="0x00000000"
				noiseVolume="0x80000000"
				volume="0x4CCCCCA8"
				pan="0x00000000"
				waveFold="0x80000000"
				lpfFrequency="0x7FFFFFFF"
				lpfResonance="0x80000000"
				lpfMorph="0x80000000"
				hpfFrequency="0x80000000"
				hpfResonance="0x80000000"
				hpfMorph="0x80000000"
				lfo1Rate="0x1999997E"
				lfo2Rate="0x00000000"
				modulator1Amount="0x80000000"
				modulator1Feedback="0x80000000"
				modulator2Amount="0x80000000"
				modulator2Feedback="0x80000000"
				carrier1Feedback="0x80000000"
				carrier2Feedback="0x80000000"
				modFXRate="0x00000000"
				modFXDepth="0x00000000"
				delayRate="0x00000000"
				delayFeedback="0x80000000"
				reverbAmount="0x80000000"
				arpeggiatorRate="0x00000000"
				stutterRate="0x00000000"
				sampleRateReduction="0x80000000"
				bitCrush="0x80000000"
				modFXOffset="0x00000000"
				modFXFeedback="0x00000000"
				compressorThreshold="0x00000000">
				<envelope1
					attack="0x80000000"
					decay="0xE6666654"
					sustain="0x7FFFFFD2"
					release="0x80000000" />
				<envelope2
					attack="0xE6666654"
					decay="0xE6666654"
					sustain="0xFFFFFFE9"
					release="0xE6666654" />
				<patchCables>
					<patchCable
						source="velocity"
						destination="volume"
						amount="0x3FFFFFE8" />
					<patchCable
						source="aftertouch"
						destination="volume"
						amount="0x2A3D7094" />
					<patchCable
						source="y"
						destination="lpfFrequency"
						amount="0x19999990" />
				</patchCables>
				<equalizer
					bass="0x00000000"
					treble="0x00000000"
					bassFrequency="0x00000000"
					trebleFrequency="0x00000000" />
			</defaultParams>
			<arpeggiator
				arpMode="off"
				noteMode="up"
				octaveMode="up"
				mpeVelocity="off"
				numOctaves="2"
				rhythm="0"
				syncType="0"
				syncLevel="7" />
			<modKnobs>
				<modKnob controlsParam="pan" />
				<modKnob controlsParam="volumePostFX" />
				<modKnob controlsParam="lpfResonance" />
				<modKnob controlsParam="lpfFrequency" />
				<modKnob controlsParam="env1Release" />
				<modKnob controlsParam="env1Attack" />
				<modKnob controlsParam="delayFeedback" />
				<modKnob controlsParam="delayRate" />
				<modKnob controlsParam="reverbAmount" />
				<modKnob controlsParam="volumePostReverbSend" patchAmountFromSource="compressor" />
				<modKnob controlsParam="pitch" patchAmountFromSource="lfo1" />
				<modKnob controlsParam="lfo1Rate" />
				<modKnob controlsParam="pitch" />
				<modKnob controlsParam="stutterRate" />
				<modKnob controlsParam="bitcrushAmount" />
				<modKnob controlsParam="sampleRateReduction" />
			</modKnobs>
		</sound>
		<sound
			name="07-perc"
			path=""
			polyphonic="auto"
			voicePriority="1"
			mode="subtractive"
			lpfMode="24dB"
			hpfMode="HPLadder"
			modFXType="none"
			filterRoute="H2L">
			<osc1
				type="sample"
				loopMode="1"
				reversed="0"
				timeStretchEnable="0"
				timeStretchAmount="0"
				fileName="SAMPLES/op1kits/acoustic_toy/07-perc.wav">
				<zone
					startSamplePos="0"
					endSamplePos="6551" />
			</osc1>
			<osc2
				type="sample"
				loopMode="0"
				reversed="0"
				timeStretchEnable="0"
				timeStretchAmount="0">
			</osc2>
			<lfo1 type="triangle" syncType="0" syncLevel="0" />
			<lfo2 type="triangle" />
			<unison num="1" detune="8" spread="0" />
			<delay
				pingPong="1"
				analog="0"
				syncType="0"
				syncLevel="7" />
			<sidechain
				syncType="0"
				syncLevel="6"
				attack="327244"
				release="936" />
			<audioCompressor
				attack="83886080"
				release="83886080"
				thresh="0"
				ratio="1073741824"
				compHPF="0" />
			<defaultParams
				arpeggiatorGate="0x00000000"
				ratchetProbability="0x80000000"
				ratchetAmount="0x80000000"
				sequenceLength="0x80000000"
				portamento="0x80000000"
				compressorShape="0xDC28F5B2"
				oscAVolume="0x7FFFFFFF"
				oscAPulseWidth="0x00000000"
				oscAWavetablePosition="0x00000000"
				oscBVolume="0x80000000"
				oscBPulseWidth="0x00000000"
				oscBWavetablePosition="0x00000000"
				noiseVolume="0x80000000"
				volume="0x4CCCCCA8"
				pan="0x00000000"
				waveFold="0x80000000"
				lpfFrequency="0x7FFFFFFF"
				lpfResonance="0x80000000"
				lpfMorph="0x80000000"
				hpfFrequency="0x80000000"
				hpfResonance="0x80000000"
				hpfMorph="0x80000000"
				lfo1Rate="0x1999997E"
				lfo2Rate="0x00000000"
				modulator1Amount="0x80000000"
				modulator1Feedback="0x80000000"
				modulator2Amount="0x80000000"
				modulator2Feedback="0x80000000"
				carrier1Feedback="0x80000000"
				carrier2Feedback="0x80000000"
				modFXRate="0x00000000"
				modFXDepth="0x00000000"
				delayRate="0x00000000"
				delayFeedback="0x80000000"
				reverbAmount="0x80000000"
				arpeggiatorRate="0x00000000"
				stutterRate="0x00000000"
				sampleRateReduction="0x80000000"
				bitCrush="0x80000000"
				modFXOffset="0x00000000"
				modFXFeedback="0x00000000"
				compressorThreshold="0x00000000">
				<envelope1
					attack="0x80000000"
					decay="0xE6666654"
					sustain="0x7FFFFFD2"
					release="0x80000000" />
				<envelope2
					attack="0xE6666654"
					decay="0xE6666654"
					sustain="0xFFFFFFE9"
					release="0xE6666654" />
				<patchCables>
					<patchCable
						source="velocity"
						destination="volume"
						amount="0x3FFFFFE8" />
					<patchCable
						source="aftertouch"
						destination="volume"
						amount="0x2A3D7094" />
					<patchCable
						source="y"
						destination="lpfFrequency"
						amount="0x19999990" />
				</patchCables>
				<equalizer
					bass="0x00000000"
					treble="0x00000000"
					bassFrequency="0x00000000"
					trebleFrequency="0x00000000" />
			</defaultParams>
			<arpeggiator
				arpMode="off"
				noteMode="up"
				octaveMode="up"
				mpeVelocity="off"
				numOctaves="2"
				rhythm="0"
				syncType="0"
				syncLevel="7" />
			<modKnobs>
				<modKnob controlsParam="pan" />
				<modKnob controlsParam="volumePostFX" />
				<modKnob controlsParam="lpfResonance" />
				<modKnob controlsParam="lpfFrequency" />
				<modKnob controlsParam="env1Release" />
				<modKnob controlsParam="env1Attack" />
				<modKnob controlsParam="delayFeedback" />
				<modKnob controlsParam="delayRate" />
				<modKnob controlsParam="reverbAmount" />
				<modKnob controlsParam="volumePostReverbSend" patchAmountFromSource="compressor" />
				<modKnob controlsParam="pitch" patchAmountFromSource="lfo1" />
				<modKnob controlsParam="lfo1Rate" />
				<modKnob controlsParam="pitch" />
				<modKnob controlsParam="stutterRate" />
				<modKnob controlsParam="bitcrushAmount" />
				<modKnob controlsParam="sampleRateReduction" />
			</modKnobs>
		</sound>
		<sound
			name="08-eight"
			path=""
			polyphonic="auto"
			voicePriority="1"
			mode="subtractive"
			lpfMode="24dB"
			hpfMode="HPLadder"
			modFXType="none"
			filterRoute="H2L">
			<osc1
				type="sample"
				loopMode="1"
				reversed="0"
				timeStretchEnable="0"
				timeStretchAmount="0"
				fileName="SAMPLES/op1kits/acoustic_toy/08-eight.wav">
				<zone
					startSamplePos="0"
					endSamplePos="12175" />
			</osc1>
			<osc2
				type="sample"
				loopMode="0"
				reversed="0"
				timeStretchEnable="0"
				timeStretchAmount="0">
			</osc2>
			<lfo1 type="triangle" syncType="0" syncLevel="0" />
			<lfo2 type="triangle" />
			<unison num="1" detune="8" spread="0" />
			<delay
				pingPong="1"
				analog="0"
				syncType="0"
				syncLevel="7" />
			<sidechain
				syncType="0"
				syncLevel="6"
				attack="327244"
				release="936" />
			<audioCompressor
				attack="83886080"
				release="83886080"
				thresh="0"
				ratio="1073741824"
				compHPF="0" />
			<defaultParams
				arpeggiatorGate="0x00000000"
				ratchetProbability="0x80000000"
				ratchetAmount="0x80000000"
				sequenceLength="0x80000000"
				portamento="0x80000000"
				compressorShape="0xDC28F5B2"
				oscAVolume="0x7FFFFFFF"
				oscAPulseWidth="0x00000000"
				oscAWavetablePosition="0x00000000"
				oscBVolume="0x80000000"
				oscBPulseWidth="0x00000000"
				oscBWavetablePosition="0x00000000"
				noiseVolume="0x80000000"
				volume="0x4CCCCCA8"
				pan="0x00000000"
				waveFold="0x80000000"
				lpfFrequency="0x7FFFFFFF"
				lpfResonance="0x80000000"
				lpfMorph="0x80000000"
				hpfFrequency="0x80000000"
				hpfResonance="0x80000000"
				hpfMorph="0x80000000"
				lfo1Rate="0x1999997E"
				lfo2Rate="0x00000000"
				modulator1Amount="0x80000000"
				modulator1Feedback="0x80000000"
				modulator2Amount="0x80000000"
				modulator2Feedback="0x80000000"
				carrier1Feedback="0x80000000"
				carrier2Feedback="0x80000000"
				modFXRate="0x00000000"
				modFXDepth="0x00000000"
				delayRate="0x00000000"
				delayFeedback="0x80000000"
				reverbAmount="0x80000000"
				arpeggiatorRate="0x00000000"
				stutterRate="0x00000000"
				sampleRateReduction="0x80000000"
				bitCrush="0x80000000"
				modFXOffset="0x00000000"
				modFXFeedback="0x00000000"
				compressorThreshold="0x00000000">
				<envelope1
					attack="0x80000000"
					decay="0xE6666654"
					sustain="0x7FFFFFD2"
					release="0x80000000" />
				<envelope2
					attack="0xE6666654"
					decay="0xE6666654"
					sustain="0xFFFFFFE9"
					release="0xE6666654" />
				<patchCables>
					<patchCable
						source="velocity"
						destination="volume"
						amount="0x3FFFFFE8" />
					<patchCable
						source="aftertouch"
						destination="volume"
						amount="0x2A3D7094" />
					<patchCable
						source="y"
						destination="lpfFrequency"
						amount="0x19999990" />
				</patchCables>
				<equalizer
					bass="0x00000000"
					treble="0x00000000"
					bassFrequency="0x00000000"
					trebleFrequency="0x00000000" />
			</defaultParams>
			<arpeggiator
				arpMode="off"
				noteMode="up"
				octaveMode="up"
				mpeVelocity="off"
				numOctaves="2"
				rhythm="0"
				syncType="0"
				syncLevel="7" />
			<modKnobs>
				<modKnob controlsParam="pan" />
				<modKnob controlsParam="volumePostFX" />
				<modKnob controlsParam="lpfResonance" />
				<modKnob controlsParam="lpfFrequency" />
				<modKnob controlsParam="env1Release" />
				<modKnob controlsParam="env1Attack" />
				<modKnob controlsParam="delayFeedback" />
				<modKnob controlsParam="delayRate" />
				<modKnob controlsParam="reverbAmount" />
				<modKnob controlsParam="volumePostReverbSend" patchAmountFromSource="compressor" />
				<modKnob controlsParam="pitch" patchAmountFromSource="lfo1" />
				<modKnob controlsParam="lfo1Rate" />
				<modKnob controlsParam="pitch" />
				<modKnob controlsParam="stutterRate" />
				<modKnob controlsParam="bitcrushAmount" />
				<modKnob controlsParam="sampleRateReduction" />
			</modKnobs>
		</sound>
		<sound
			name="09-hat"
			path=""
			polyphonic="auto"
			voicePriority="1"
			mode="subtractive"
			lpfMode="24dB"
			hpfMode="HPLadder"
			modFXType="none"
			filterRoute="H2L">
			<osc1
				type="sample"
				loopMode="1"
				reversed="0"
				timeStretchEnable="0"
				timeStretchAmount="0"
				fileName="SAMPLES/op1kits/acoustic_toy/09-hat.wav">
				<zone
					startSamplePos="0"
					endSamplePos="7534" />
			</osc1>
			<osc2
				type="sample"
				loopMode="0"
				reversed="0"
				timeStretchEnable="0"
				timeStretchAmount="0">
			</osc2>
			<lfo1 type="triangle" syncType="0" syncLevel="0" />
			<lfo2 type="triangle" />
			<unison num="1" detune="8" spread="0" />
			<delay
				pingPong="1"
				analog="0"
				syncType="0"
				syncLevel="7" />
			<sidechain
				syncType="0"
				syncLevel="6"
				attack="327244"
				release="936" />
			<audioCompressor
				attack="83886080"
				release="83886080"
				thresh="0"
				ratio="1073741824"
				compHPF="0" />
			<defaultParams
				arpeggiatorGate="0x00000000"
				ratchetProbability="0x80000000"
				ratchetAmount="0x80000000"
				sequenceLength="0x80000000"
				portamento="0x80000000"
				compressorShape="0xDC28F5B2"
				oscAVolume="0x7FFFFFFF"
				oscAPulseWidth="0x00000000"
				oscAWavetablePosition="0x00000000"
				oscBVolume="0x80000000"
				oscBPulseWidth="0x00000000"
				oscBWavetablePosition="0x00000000"
				noiseVolume="0x80000000"
				volume="0x4CCCCCA8"
				pan="0x00000000"
				waveFold="0x80000000"
				lpfFrequency="0x7FFFFFFF"
				lpfResonance="0x80000000"
				lpfMorph="0x80000000"
				hpfFrequency="0x80000000"
				hpfResonance="0x80000000"
				hpfMorph="0x80000000"
				lfo1Rate="0x1999997E"
				lfo2Rate="0x00000000"
				modulator1Amount="0x80000000"
				modulator1Feedback="0x80000000"
				modulator2Amount="0x80000000"
				modulator2Feedback="0x80000000"
				carrier1Feedback="0x80000000"
				carrier2Feedback="0x80000000"
				modFXRate="0x00000000"
				modFXDepth="0x00000000"
				delayRate="0x00000000"
				delayFeedback="0x80000000"
				reverbAmount="0x80000000"
				arpeggiatorRate="0x00000000"
				stutterRate="0x00000000"
				sampleRateReduction="0x80000000"
				bitCrush="0x80000000"
				modFXOffset="0x00000000"
				modFXFeedback="0x00000000"
				compressorThreshold="0x00000000">
				<envelope1
					attack="0x80000000"
					decay="0xE6666654"
					sustain="0x7FFFFFD2"
					release="0x80000000" />
				<envelope2
					attack="0xE6666654"
					decay="0xE6666654"
					sustain="0xFFFFFFE9"
					release="0xE6666654" />
				<patchCables>
					<patchCable
						source="velocity"
						destination="volume"
						amount="0x3FFFFFE8" />
					<patchCable
						source="aftertouch"
						destination="volume"
						amount="0x2A3D7094" />
					<patchCable
						source="y"
						destination="lpfFrequency"
						amount="0x19999990" />
				</patchCables>
				<equalizer
					bass="0x00000000"
					treble="0x00000000"
					bassFrequency="0x00000000"
					trebleFrequency="0x00000000" />
			</defaultParams>
			<arpeggiator
				arpMode="off"
				noteMode="up"
				octaveMode="up"
				mpeVelocity="off"
				numOctaves="2"
				rhythm="0"
				syncType="0"
				syncLevel="7" />
			<modKnobs>
				<modKnob controlsParam="pan" />
				<modKnob controlsParam="volumePostFX" />
				<modKnob controlsParam="lpfResonance" />
				<modKnob controlsParam="lpfFrequency" />
				<modKnob controlsParam="env1Release" />
				<modKnob controlsParam="env1Attack" />
				<modKnob controlsParam="delayFeedback" />
				<modKnob controlsParam="delayRate" />
				<modKnob controlsParam="reverbAmount" />
				<modKnob controlsParam="volumePostReverbSend" patchAmountFromSource="compressor" />
				<modKnob controlsParam="pitch" patchAmountFromSource="lfo1" />
				<modKnob controlsParam="lfo1Rate" />
				<modKnob controlsParam="pitch" />
				<modKnob controlsParam="stutterRate" />
				<modKnob controlsParam="bitcrushAmount" />
				<modKnob controlsParam="sampleRateReduction" />
			</modKnobs>
		</sound>
		<sound
			name="10-pedal"
			path=""
			polyphonic="auto"
			voicePriority="1"
			mode="subtractive"
			lpfMode="24dB"
			hpfMode="HPLadder"
			modFXType="none"
			filterRoute="H2L">
			<osc1
				type="sample"
				loopMode="1"
				reversed="0"
				timeStretchEnable="0"
				timeStretchAmount="0"
				fileName="SAMPLES/op1kits/acoustic_toy/10-pedal.wav">
				<zone
					startSamplePos="0"
					endSamplePos="16220" />
			</osc1>
			<osc2
				type="sample"
				loopMode="0"
				reversed="0"
				timeStretchEnable="0"
				timeStretchAmount="0">
			</osc2>
			<lfo1 type="triangle" syncType="0" syncLevel="0" />
			<lfo2 type="triangle" />
			<unison num="1" detune="8" spread="0" />
			<delay
				pingPong="1"
				analog="0"
				syncType="0"
				syncLevel="7" />
			<sidechain
				syncType="0"
				syncLevel="6"
				attack="327244"
				release="936" />
			<audioCompressor
				attack="83886080"
				release="83886080"
				thresh="0"
				ratio="1073741824"
				compHPF="0" />
			<defaultParams
				arpeggiatorGate="0x00000000"
				ratchetProbability="0x80000000"
				ratchetAmount="0x80000000"
				sequenceLength="0x80000000"
				portamento="0x80000000"
				compressorShape="0xDC28F5B2"
				oscAVolume="0x7FFFFFFF"
				oscAPulseWidth="0x00000000"
				oscAWavetablePosition="0x00000000"
				oscBVolume="0x80000000"
				oscBPulseWidth="0x00000000"
				oscBWavetablePosition="0x00000000"
				noiseVolume="0x80000000"
				volume="0x4CCCCCA8"
				pan="0x00000000"
				waveFold="0x80000000"
				lpfFrequency="0x7FFFFFFF"
				lpfResonance="0x80000000"
				lpfMorph="0x80000000"
				hpfFrequency="0x80000000"
				hpfResonance="0x80000000"
				hpfMorph="0x80000000"
				lfo1Rate="0x1999997E"
				lfo2Rate="0x00000000"
				modulator1Amount="0x80000000"
				modulator1Feedback="0x80000000"
				modulator2Amount="0x80000000"
				modulator2Feedback="0x80000000"
				carrier1Feedback="0x80000000"
				carrier2Feedback="0x80000000"
				modFXRate="0x00000000"
				modFXDepth="0x00000000"
				delayRate="0x00000000"
				delayFeedback="0x80000000"
				reverbAmount="0x80000000"
				arpeggiatorRate="0x00000000"
				stutterRate="0x00000000"
				sampleRateReduction="0x80000000"
				bitCrush="0x80000000"
				modFXOffset="0x00000000"
				modFXFeedback="0x00000000"
				compressorThreshold="0x00000000">
				<envelope1
					attack="0x80000000"
					decay="0xE6666654"
					sustain="0x7FFFFFD2"
					release="0x80000000" />
				<envelope2
					attack="0xE6666654"
					decay="0xE6666654"
					sustain="0xFFFFFFE9"
					release="0xE6666654" />
				<patchCables>
					<patchCable
						source="velocity"
						destination="volume"
						amount="0x3FFFFFE8" />
					<patchCable
						source="aftertouch"
						destination="volume"
						amount="0x2A3D7094" />
					<patchCable
						source="y"
						destination="lpfFrequency"
						amount="0x19999990" />
				</patchCables>
				<equalizer
					bass="0x00000000"
					treble="0x00000000"
					bassFrequency="0x00000000"
					trebleFrequency="0x00000000" />
			</defaultParams>
			<arpeggiator
				arpMode="off"
				noteMode="up"
				octaveMode="up"
				mpeVelocity="off"
				numOctaves="2"
				rhythm="0"
				syncType="0"
				syncLevel="7" />
			<modKnobs>
				<modKnob controlsParam="pan" />
				<modKnob controlsParam="volumePostFX" />
				<modKnob controlsParam="lpfResonance" />
				<modKnob controlsParam="lpfFrequency" />
				<modKnob controlsParam="env1Release" />
				<modKnob controlsParam="env1Attack" />
				<modKnob controlsParam="delayFeedback" />
				<modKnob controlsParam="delayRate" />
				<modKnob controlsParam="reverbAmount" />
				<modKnob controlsParam="volumePostReverbSend" patchAmountFromSource="compressor" />
				<modKnob controlsParam="pitch" patchAmountFromSource="lfo1" />
				<modKnob controlsParam="lfo1Rate" />
				<modKnob controlsParam="pitch" />
				<modKnob controlsParam="stutterRate" />
				<modKnob controlsParam="bitcrushAmount" />
				<modKnob controlsParam="sampleRateReduction" />
			</modKnobs>
		</sound>
		<sound
			name="11-open_hat"
			path=""
			polyphonic="auto"
			voicePriority="1"
			mode="subtractive"
			lpfMode="24dB"
			hpfMode="HPLadder"
			modFXType="none"
			filterRoute="H2L">
			<osc1
				type="sample"
				loopMode="1"
				reversed="0"
				timeStretchEnable="0"
				timeStretchAmount="0"
				fileName="SAMPLES/op1kits/acoustic_toy/11-open_hat.wav">
				<zone
					startSamplePos="0"
					endSamplePos="55502" />
			</osc1>
			<osc2
				type="sample"
				loopMode="0"
				reversed="0"
				timeStretchEnable="0"
				timeStretchAmount="0">
			</osc2>
			<lfo1 type="triangle" syncType="0" syncLevel="0" />
			<lfo2 type="triangle" />
			<unison num="1" detune="8" spread="0" />
			<delay
				pingPong="1"
				analog="0"
				syncType="0"
				syncLevel="7" />
			<sidechain
				syncType="0"
				syncLevel="6"
				attack="327244"
				release="936" />
			<audioCompressor
				attack="83886080"
				release="83886080"
				thresh="0"
				ratio="1073741824"
				compHPF="0" />
			<defaultParams
				arpeggiatorGate="0x00000000"
				ratchetProbability="0x80000000"
				ratchetAmount="0x80000000"
				sequenceLength="0x80000000"
				portamento="0x80000000"
				compressorShape="0xDC28F5B2"
				oscAVolume="0x7FFFFFFF"
				oscAPulseWidth="0x00000000"
				oscAWavetablePosition="0x00000000"
				oscBVolume="0x80000000"
				oscBPulseWidth="0x00000000"
				oscBWavetablePosition="0x00000000"
				noiseVolume="0x80000000"
				volume="0x4CCCCCA8"
				pan="0x00000000"
				waveFold="0x80000000"
				lpfFrequency="0x7FFFFFFF"
				lpfResonance="0x80000000"
				lpfMorph="0x80000000"
				hpfFrequency="0x80000000"
				hpfResonance="0x80000000"
				hpfMorph="0x80000000"
				lfo1Rate="0x1999997E"
				lfo2Rate="0x00000000"
				modulator1Amount="0x80000000"
				modulator1Feedback="0x80000000"
				modulator2Amount="0x80000000"
				modulator2Feedback="0x80000000"
				carrier1Feedback="0x80000000"
				carrier2Feedback="0x80000000"
				modFXRate="0x00000000"
				modFXDepth="0x00000000"
				delayRate="0x00000000"
				delayFeedback="0x80000000"
				reverbAmount="0x80000000"
				arpeggiatorRate="0x00000000"
				stutterRate="0x00000000"
				sampleRateReduction="0x80000000"
				bitCrush="0x80000000"
				modFXOffset="0x00000000"
				modFXFeedback="0x00000000"
				compressorThreshold="0x00000000">
				<envelope1
					attack="0x80000000"
					decay="0xE6666654"
					sustain="0x7FFFFFD2"
					release="0x80000000" />
				<envelope2
					attack="0xE6666654"
					decay="0xE6666654"
					sustain="0xFFFFFFE9"
					release="0xE6666654" />
				<patchCables>
					<patchCable
						source="velocity"
						destination="volume"
						amount="0x3FFFFFE8" />
					<patchCable
						source="aftertouch"
						destination="volume"
						amount="0x2A3D7094" />
					<patchCable
						source="y"
						destination="lpfFrequency"
						amount="0x19999990" />
				</patchCables>
				<equalizer
					bass="0x00000000"
					treble="0x00000000"
					bassFrequency="0x00000000"
					trebleFrequency="0x00000000" />
			</defaultParams>
			<arpeggiator
				arpMode="off"
				noteMode="up"
				octaveMode="up"
				mpeVelocity="off"
				numOctaves="2"
				rhythm="0"
				syncType="0"
				syncLevel="7" />
			<modKnobs>
				<modKnob controlsParam="pan" />
				<modKnob controlsParam="volumePostFX" />
				<modKnob controlsParam="lpfResonance" />
				<modKnob controlsParam="lpfFrequency" />
				<modKnob controlsParam="env1Release" />
				<modKnob controlsParam="env1Attack" />
				<modKnob controlsParam="delayFeedback" />
				<modKnob controlsParam="delayRate" />
				<modKnob controlsParam="reverbAmount" />
				<modKnob controlsParam="volumePostReverbSend" patchAmountFromSource="compressor" />
				<modKnob controlsParam="pitch" patchAmountFromSource="lfo1" />
				<modKnob controlsParam="lfo1Rate" />
				<modKnob controlsParam="pitch" />
				<modKnob controlsParam="stutterRate" />
				<modKnob controlsParam="bitcrushAmount" />
				<modKnob controlsParam="sampleRateReduction" />
			</modKnobs>
		</sound>
		<sound
			name="12-ten"
			path=""
			polyphonic="auto"
			voicePriority="1"
			mode="subtractive"
			lpfMode="24dB"
			hpfMode="HPLadder"
			modFXType="none"
			filterRoute="H2L">
			<osc1
				type="sample"
				loopMode="1"
				reversed="0"
				timeStretchEnable="0"
				timeStretchAmount="0"
				fileName="SAMPLES/op1kits/acoustic_toy/12-ten.wav">
				<zone
					startSamplePos="0"
					endSamplePos="13064" />
			</osc1>
			<osc2
				type="sample"
				loopMode="0"
				reversed="0"
				timeStretchEnable="0"
				timeStretchAmount="0">
			</osc2>
			<lfo1 type="triangle" syncType="0" syncLevel="0" />
			<lfo2 type="triangle" />
			<unison num="1" detune="8" spread="0" />
			<delay
				pingPong="1"
				analog="0"
				syncType="0"
				syncLevel="7" />
			<sidechain
				syncType="0"
				syncLevel="6"
				attack="327244"
				release="936" />
			<audioCompressor
				attack="83886080"
				release="83886080"
				thresh="0"
				ratio="1073741824"
				compHPF="0" />
			<defaultParams
				arpeggiatorGate="0x00000000"
				ratchetProbability="0x80000000"
				ratchetAmount="0x80000000"
				sequenceLength="0x80000000"
				portamento="0x80000000"
				compressorShape="0xDC28F5B2"
				oscAVolume="0x7FFFFFFF"
				oscAPulseWidth="0x00000000"
				oscAWavetablePosition="0x00000000"
				oscBVolume="0x80000000"
				oscBPulseWidth="0x00000000"
				oscBWavetablePosition="0x00000000"
				noiseVolume="0x80000000"
				volume="0x4CCCCCA8"
				pan="0x00000000"
				waveFold="0x80000000"
				lpfFrequency="0x7FFFFFFF"
				lpfResonance="0x80000000"
				lpfMorph="0x80000000"
				hpfFrequency="0x80000000"
				hpfResonance="0x80000000"
				hpfMorph="0x80000000"
				lfo1Rate="0x1999997E"
				lfo2Rate="0x00000000"
				modulator1Amount="0x80000000"
				modulator1Feedback="0x80000000"
				modulator2Amount="0x80000000"
				modulator2Feedback="0x80000000"
				carrier1Feedback="0x80000000"
				carrier2Feedback="0x80000000"
				modFXRate="0x00000000"
				modFXDepth="0x00000000"
				delayRate="0x00000000"
				delayFeedback="0x80000000"
				reverbAmount="0x80000000"
				arpeggiatorRate="0x00000000"
				stutterRate="0x00000000"
				sampleRateReduction="0x80000000"
				bitCrush="0x80000000"
				modFXOffset="0x00000000"
				modFXFeedback="0x00000000"
				compressorThreshold="0x00000000">
				<envelope1
					attack="0x80000000"
					decay="0xE6666654"
					sustain="0x7FFFFFD2"
					release="0x80000000" />
				<envelope2
					attack="0xE6666654"
					decay="0xE6666654"
					sustain="0xFFFFFFE9"
					release="0xE6666654" />
				<patchCables>
					<patchCable
						source="velocity"
						destination="volume"
						amount="0x3FFFFFE8" />
					<patchCable
						source="aftertouch"
						destination="volume"
						amount="0x2A3D7094" />
					<patchCable
						source="y"
						destination="lpfFrequency"
						amount="0x19999990" />
				</patchCables>
				<equalizer
					bass="0x00000000"
					treble="0x00000000"
					bassFrequency="0x00000000"
					trebleFrequency="0x00000000" />
			</defaultParams>
			<arpeggiator
				arpMode="off"
				noteMode="up"
				octaveMode="up"
				mpeVelocity="off"
				numOctaves="2"
				rhythm="0"
				syncType="0"
				syncLevel="7" />
			<modKnobs>
				<modKnob controlsParam="pan" />
				<modKnob controlsParam="volumePostFX" />
				<modKnob controlsParam="lpfResonance" />
				<modKnob controlsParam="lpfFrequency" />
				<modKnob controlsParam="env1Release" />
				<modKnob controlsParam="env1Attack" />
				<modKnob controlsParam="delayFeedback" />
				<modKnob controlsParam="delayRate" />
				<modKnob controlsParam="reverbAmount" />
				<modKnob controlsParam="volumePostReverbSend" patchAmountFromSource="compressor" />
				<modKnob controlsParam="pitch" patchAmountFromSource="lfo1" />
				<modKnob controlsParam="lfo1Rate" />
				<modKnob controlsParam="pitch" />
				<modKnob controlsParam="stutterRate" />
				<modKnob controlsParam="bitcrushAmount" />
				<modKnob controlsParam="sampleRateReduction" />
			</modKnobs>
		</sound>
		<sound
			name="13-eleven"
			path=""
			polyphonic="auto"
			voicePriority="1"
			mode="subtractive"
			lpfMode="24dB"
			hpfMode="HPLadder"
			modFXType="none"
			filterRoute="H2L">
			<osc1
				type="sample"
				loopMode="1"
				reversed="0"
				timeStretchEnable="0"
				timeStretchAmount="0"
				fileName="SAMPLES/op1kits/acoustic_toy/13-eleven.wav">
				<zone
					startSamplePos="0"
					endSamplePos="17905" />
			</osc1>
			<osc2
				type="sample"
				loopMode="0"
				reversed="0"
				timeStretchEnable="0"
				timeStretchAmount="0">
			</osc2>
			<lfo1 type="triangle" syncType="0" syncLevel="0" />
			<lfo2 type="triangle" />
			<unison num="1" detune="8" spread="0" />
			<delay
				pingPong="1"
				analog="0"
				syncType="0"
				syncLevel="7" />
			<sidechain
				syncType="0"
				syncLevel="6"
				attack="327244"
				release="936" />
			<audioCompressor
				attack="83886080"
				release="83886080"
				thresh="0"
				ratio="1073741824"
				compHPF="0" />
			<defaultParams
				arpeggiatorGate="0x00000000"
				ratchetProbability="0x80000000"
				ratchetAmount="0x80000000"
				sequenceLength="0x80000000"
				portamento="0x80000000"
				compressorShape="0xDC28F5B2"
				oscAVolume="0x7FFFFFFF"
				oscAPulseWidth="0x00000000"
				oscAWavetablePosition="0x00000000"
				oscBVolume="0x80000000"
				oscBPulseWidth="0x00000000"
				oscBWavetablePosition="0x00000000"
				noiseVolume="0x80000000"
				volume="0x4CCCCCA8"
				pan="0x00000000"
				waveFold="0x80000000"
				lpfFrequency="0x7FFFFFFF"
				lpfResonance="0x80000000"
				lpfMorph="0x80000000"
				hpfFrequency="0x80000000"
				hpfResonance="0x80000000"
				hpfMorph="0x80000000"
				lfo1Rate="0x1999997E"
				lfo2Rate="0x00000000"
				modulator1Amount="0x80000000"
				modulator1Feedback="0x80000000"
				modulator2Amount="0x80000000"
				modulator2Feedback="0x80000000"
				carrier1Feedback="0x80000000"
				carrier2Feedback="0x80000000"
				modFXRate="0x00000000"
				modFXDepth="0x00000000"
				delayRate="0x00000000"
				delayFeedback="0x80000000"
				reverbAmount="0x80000000"
				arpeggiatorRate="0x00000000"
				stutterRate="0x00000000"
				sampleRateReduction="0x80000000"
				bitCrush="0x80000000"
				modFXOffset="0x00000000"
				modFXFeedback="0x00000000"
				compressorThreshold="0x00000000">
				<envelope1
					attack="0x80000000"
					decay="0xE6666654"
					sustain="0x7FFFFFD2"
					release="0x80000000" />
				<envelope2
					attack="0xE6666654"
					decay="0xE6666654"
					sustain="0xFFFFFFE9"
					release="0xE6666654" />
				<patchCables>
					<patchCable
						source="velocity"
						destination="volume"
						amount="0x3FFFFFE8" />
					<patchCable
						source="aftertouch"
						destination="volume"
						amount="0x2A3D7094" />
					<patchCable
						source="y"
						destination="lpfFrequency"
						amount="0x19999990" />
				</patchCables>
				<equalizer
					bass="0x00000000"
					treble="0x00000000"
					bassFrequency="0x00000000"
					trebleFrequency="0x00000000" />
			</defaultParams>
			<arpeggiator
				arpMode="off"
				noteMode="up"
				octaveMode="up"
				mpeVelocity="off"
				numOctaves="2"
				rhythm="0"
				syncType="0"
				syncLevel="7" />
			<modKnobs>
				<modKnob controlsParam="pan" />
				<modKnob controlsParam="volumePostFX" />
				<modKnob controlsParam="lpfResonance" />
				<modKnob controlsParam="lpfFrequency" />
				<modKnob controlsParam="env1Release" />
				<modKnob controlsParam="env1Attack" />
				<modKnob controlsParam="delayFeedback" />
				<modKnob controlsParam="delayRate" />
				<modKnob controlsParam="reverbAmount" />
				<modKnob controlsParam="volumePostReverbSend" patchAmountFromSource="compressor" />
				<modKnob controlsParam="pitch" patchAmountFromSource="lfo1" />
				<modKnob controlsParam="lfo1Rate" />
				<modKnob controlsParam="pitch" />
				<modKnob controlsParam="stutterRate" />
				<modKnob controlsParam="bitcrushAmount" />
				<modKnob controlsParam="sampleRateReduction" />
			</modKnobs>
		</sound>
		<sound
			name="14-ride"
			path=""
			polyphonic="auto"
			voicePriority="1"
			mode="subtractive"
			lpfMode="24dB"
			hpfMode="HPLadder"
			modFXType="none"
			filterRoute="H2L">
			<osc1
				type="sample"
				loopMode="1"
				reversed="0"
				timeStretchEnable="0"
				timeStretchAmount="0"
				fileName="SAMPLES/op1kits/acoustic_toy/14-ride.wav">
				<zone
					startSamplePos="0"
					endSamplePos="58922" />
			</osc1>
			<osc2
				type="sample"
				loopMode="0"
				reversed="0"
				timeStretchEnable="0"
				timeStretchAmount="0">
			</osc2>
			<lfo1 type="triangle" syncType="0" syncLevel="0" />
			<lfo2 type="triangle" />
			<unison num="1" detune="8" spread="0" />
			<delay
				pingPong="1"
				analog="0"
				syncType="0"
				syncLevel="7" />
			<sidechain
				syncType="0"
				syncLevel="6"
				attack="327244"
				release="936" />
			<audioCompressor
				attack="83886080"
				release="83886080"
				thresh="0"
				ratio="1073741824"
				compHPF="0" />
			<defaultParams
				arpeggiatorGate="0x00000000"
				ratchetProbability="0x80000000"
				ratchetAmount="0x80000000"
				sequenceLength="0x80000000"
				portamento="0x80000000"
				compressorShape="0xDC28F5B2"
				oscAVolume="0x7FFFFFFF"
				oscAPulseWidth="0x00000000"
				oscAWavetablePosition="0x00000000"
				oscBVolume="0x80000000"
				oscBPulseWidth="0x00000000"
				oscBWavetablePosition="0x00000000"
				noiseVolume="0x80000000"
				volume="0x4CCCCCA8"
				pan="0x00000000"
				waveFold="0x80000000"
				lpfFrequency="0x7FFFFFFF"
				lpfResonance="0x80000000"
				lpfMorph="0x80000000"
				hpfFrequency="0x80000000"
				hpfResonance="0x80000000"
				hpfMorph="0x80000000"
				lfo1Rate="0x1999997E"
				lfo2Rate="0x00000000"
				modulator1Amount="0x80000000"
				modulator1Feedback="0x80000000"
				modulator2Amount="0x80000000"
				modulator2Feedback="0x80000000"
				carrier1Feedback="0x80000000"
				carrier2Feedback="0x80000000"
				modFXRate="0x00000000"
				modFXDepth="0x00000000"
				delayRate="0x00000000"
				delayFeedback="0x80000000"
				reverbAmount="0x80000000"
				arpeggiatorRate="0x00000000"
				stutterRate="0x00000000"
				sampleRateReduction="0x80000000"
				bitCrush="0x80000000"
				modFXOffset="0x00000000"
				modFXFeedback="0x00000000"
				compressorThreshold="0x00000000">
				<envelope1
					attack="0x80000000"
					decay="0xE6666654"
					sustain="0x7FFFFFD2"
					release="0x80000000" />
				<envelope2
					attack="0xE6666654"
					decay="0xE6666654"
					sustain="0xFFFFFFE9"
					release="0xE6666654" />
				<patchCables>
					<patchCable
						source="velocity"
						destination="volume"
						amount="0x3FFFFFE8" />
					<patchCable
						source="aftertouch"
						destination="volume"
						amount="0x2A3D7094" />
					<patchCable
						source="y"
						destination="lpfFrequency"
						amount="0x19999990" />
				</patchCables>
				<equalizer
					bass="0x00000000"
					treble="0x00000000"
					bassFrequency="0x00000000"
					trebleFrequency="0x00000000" />
			</defaultParams>
			<arpeggiator
				arpMode="off"
				noteMode="up"
				octaveMode="up"
				mpeVelocity="off"
				numOctaves="2"
				rhythm="0"
				syncType="0"
				syncLevel="7" />
			<modKnobs>
				<modKnob controlsParam="pan" />
				<modKnob controlsParam="volumePostFX" />
				<modKnob controlsParam="lpfResonance" />
				<modKnob controlsParam="lpfFrequency" />
				<modKnob controlsParam="env1Release" />
				<modKnob controlsParam="env1Attack" />
				<modKnob controlsParam="delayFeedback" />
				<modKnob controlsParam="delayRate" />
				<modKnob controlsParam="reverbAmount" />
				<modKnob controlsParam="volumePostReverbSend" patchAmountFromSource="compressor" />
				<modKnob controlsParam="pitch" patchAmountFromSource="lfo1" />
				<modKnob controlsParam="lfo1Rate" />
				<modKnob controlsParam="pitch" />
				<modKnob controlsParam="stutterRate" />
				<modKnob controlsParam="bitcrushAmount" />
				<modKnob controlsParam="sampleRateReduction" />
			</modKnobs>
		</sound>
		<sound
			name="15-twelve"
			path=""
			polyphonic="auto"
			voicePriority="1"
			mode="subtractive"
			lpfMode="24dB"
			hpfMode="HPLadder"
			modFXType="none"
			filterRoute="H2L">
			<osc1
				type="sample"
				loopMode="1"
				reversed="0"
				timeStretchEnable="0"
				timeStretchAmount="0"
				fileName="SAMPLES/op1kits/acoustic_toy/15-twelve.wav">
				<zone
					startSamplePos="0"
					endSamplePos="40270" />
			</osc1>
			<osc2
				type="sample"
				loopMode="0"
				reversed="0"
				timeStretchEnable="0"
				timeStretchAmount="0">
			</osc2>
			<lfo1 type="triangle" syncType="0" syncLevel="0" />
			<lfo2 type="triangle" />
			<unison num="1" detune="8" spread="0" />
			<delay
				pingPong="1"
				analog="0"
				syncType="0"
				syncLevel="7" />
			<sidechain
				syncType="0"
				syncLevel="6"
				attack="327244"
				release="936" />
			<audioCompressor
				attack="83886080"
				release="83886080"
				thresh="0"
				ratio="1073741824"
				compHPF="0" />
			<defaultParams
				arpeggiatorGate="0x00000000"
				ratchetProbability="0x80000000"
				ratchetAmount="0x80000000"
				sequenceLength="0x80000000"
				portamento="0x80000000"
				compressorShape="0xDC28F5B2"
				oscAVolume="0x7FFFFFFF"
				oscAPulseWidth="0x00000000"
				oscAWavetablePosition="0x00000000"
				oscBVolume="0x80000000"
				oscBPulseWidth="0x00000000"
				oscBWavetablePosition="0x00000000"
				noiseVolume="0x80000000"
				volume="0x4CCCCCA8"
				pan="0x00000000"
				waveFold="0x80000000"
				lpfFrequency="0x7FFFFFFF"
				lpfResonance="0x80000000"
				lpfMorph="0x80000000"
				hpfFrequency="0x80000000"
				hpfResonance="0x80000000"
				hpfMorph="0x80000000"
				lfo1Rate="0x1999997E"
				lfo2Rate="0x00000000"
				modulator1Amount="0x80000000"
				modulator1Feedback="0x80000000"
				modulator2Amount="0x80000000"
				modulator2Feedback="0x80000000"
				carrier1Feedback="0x80000000"
				carrier2Feedback="0x80000000"
				modFXRate="0x00000000"
				modFXDepth="0x00000000"
				delayRate="0x00000000"
				delayFeedback="0x80000000"
				reverbAmount="0x80000000"
				arpeggiatorRate="0x00000000"
				stutterRate="0x00000000"
				sampleRateReduction="0x80000000"
				bitCrush="0x80000000"
				modFXOffset="0x00000000"
				modFXFeedback="0x00000000"
				compressorThreshold="0x00000000">
				<envelope1
					attack="0x80000000"
					decay="0xE6666654"
					sustain="0x7FFFFFD2"
					release="0x80000000" />
				<envelope2
					attack="0xE6666654"
					decay="0xE6666654"
					sustain="0xFFFFFFE9"
					release="0xE6666654" />
				<patchCables>
					<patchCable
						source="velocity"
						destination="volume"
						amount="0x3FFFFFE8" />
					<patchCable
						source="aftertouch"
						destination="volume"
						amount="0x2A3D7094" />
					<patchCable
						source="y"
						destination="lpfFrequency"
						amount="0x19999990" />
				</patchCables>
				<equalizer
					bass="0x00000000"
					treble="0x00000000"
					bassFrequency="0x00000000"
					trebleFrequency="0x00000000" />
			</defaultParams>
			<arpeggiator
				arpMode="off"
				noteMode="up"
				octaveMode="up"
				mpeVelocity="off"
				numOctaves="2"
				rhythm="0"
				syncType="0"
				syncLevel="7" />
			<modKnobs>
				<modKnob controlsParam="pan" />
				<modKnob controlsParam="volumePostFX" />
				<modKnob controlsParam="lpfResonance" />
				<modKnob controlsParam="lpfFrequency" />
				<modKnob controlsParam="env1Release" />
				<modKnob controlsParam="env1Attack" />
				<modKnob controlsParam="delayFeedback" />
				<modKnob controlsParam="delayRate" />
				<modKnob controlsParam="reverbAmount" />
				<modKnob controlsParam="volumePostReverbSend" patchAmountFromSource="compressor" />
				<modKnob controlsParam="pitch" patchAmountFromSource="lfo1" />
				<modKnob controlsParam="lfo1Rate" />
				<modKnob controlsParam="pitch" />
				<modKnob controlsParam="stutterRate" />
				<modKnob controlsParam="bitcrushAmount" />
				<modKnob controlsParam="sampleRateReduction" />
			</modKnobs>
		</sound>
		<sound
			name="16-crash"
			path=""
			polyphonic="auto"
			voicePriority="1"
			mode="subtractive"
			lpfMode="24dB"
			hpfMode="HPLadder"
			modFXType="none"
			filterRoute="H2L">
			<osc1
				type="sample"
				loopMode="1"
				reversed="0"
				timeStretchEnable="0"
				timeStretchAmount="0"
				fileName="SAMPLES/op1kits/acoustic_toy/16-crash.wav">
				<zone
					startSamplePos="0"
					endSamplePos="43660" />
			</osc1>
			<osc2
				type="sample"
				loopMode="0"
				reversed="0"
				timeStretchEnable="0"
				timeStretchAmount="0">
			</osc2>
			<lfo1 type="triangle" syncType="0" syncLevel="0" />
			<lfo2 type="triangle" />
			<unison num="1" detune="8" spread="0" />
			<delay
				pingPong="1"
				analog="0"
				syncType="0"
				syncLevel="7" />
			<sidechain
				syncType="0"
				syncLevel="6"
				attack="327244"
				release="936" />
			<audioCompressor
				attack="83886080"
				release="83886080"
				thresh="0"
				ratio="1073741824"
				compHPF="0" />
			<defaultParams
				arpeggiatorGate="0x00000000"
				ratchetProbability="0x80000000"
				ratchetAmount="0x80000000"
				sequenceLength="0x80000000"
				portamento="0x80000000"
				compressorShape="0xDC28F5B2"
				oscAVolume="0x7FFFFFFF"
				oscAPulseWidth="0x00000000"
				oscAWavetablePosition="0x00000000"
				oscBVolume="0x80000000"
				oscBPulseWidth="0x00000000"
				oscBWavetablePosition="0x00000000"
				noiseVolume="0x80000000"
				volume="0x4CCCCCA8"
				pan="0x00000000"
				waveFold="0x80000000"
				lpfFrequency="0x7FFFFFFF"
				lpfResonance="0x80000000"
				lpfMorph="0x80000000"
				hpfFrequency="0x80000000"
				hpfResonance="0x80000000"
				hpfMorph="0x80000000"
				lfo1Rate="0x1999997E"
				lfo2Rate="0x00000000"
				modulator1Amount="0x80000000"
				modulator1Feedback="0x80000000"
				modulator2Amount="0x80000000"
				modulator2Feedback="0x80000000"
				carrier1Feedback="0x80000000"
				carrier2Feedback="0x80000000"
				modFXRate="0x00000000"
				modFXDepth="0x00000000"
				delayRate="0x00000000"
				delayFeedback="0x80000000"
				reverbAmount="0x80000000"
				arpeggiatorRate="0x00000000"
				stutterRate="0x00000000"
				sampleRateReduction="0x80000000"
				bitCrush="0x80000000"
				modFXOffset="0x00000000"
				modFXFeedback="0x00000000"
				compressorThreshold="0x00000000">
				<envelope1
					attack="0x80000000"
					decay="0xE6666654"
					sustain="0x7FFFFFD2"
					release="0x80000000" />
				<envelope2
					attack="0xE6666654"
					decay="0xE6666654"
					sustain="0xFFFFFFE9"
					release="0xE6666654" />
				<patchCables>
					<patchCable
						source="velocity"
						destination="volume"
						amount="0x3FFFFFE8" />
					<patchCable
						source="aftertouch"
						destination="volume"
						amount="0x2A3D7094" />
					<patchCable
						source="y"
						destination="lpfFrequency"
						amount="0x19999990" />
				</patchCables>
				<equalizer
					bass="0x00000000"
					treble="0x00000000"
					bassFrequency="0x00000000"
					trebleFrequency="0x00000000" />
			</defaultParams>
			<arpeggiator
				arpMode="off"
				noteMode="up"
				octaveMode="up"
				mpeVelocity="off"
				numOctaves="2"
				rhythm="0"
				syncType="0"
				syncLevel="7" />
			<modKnobs>
				<modKnob controlsParam="pan" />
				<modKnob controlsParam="volumePostFX" />
				<modKnob controlsParam="lpfResonance" />
				<modKnob controlsParam="lpfFrequency" />
				<modKnob controlsParam="env1Release" />
				<modKnob controlsParam="env1Attack" />
				<modKnob controlsParam="delayFeedback" />
				<modKnob controlsParam="delayRate" />
				<modKnob controlsParam="reverbAmount" />
				<modKnob controlsParam="volumePostReverbSend" patchAmountFromSource="compressor" />
				<modKnob controlsParam="pitch" patchAmountFromSource="lfo1" />
				<modKnob controlsParam="lfo1Rate" />
				<modKnob controlsParam="pitch" />
				<modKnob controlsParam="stutterRate" />
				<modKnob controlsParam="bitcrushAmount" />
				<modKnob controlsParam="sampleRateReduction" />
			</modKnobs>
		</sound>
		<sound
			name="17-noot"
			path=""
			polyphonic="auto"
			voicePriority="1"
			mode="subtractive"
			lpfMode="24dB"
			hpfMode="HPLadder"
			modFXType="none"
			filterRoute="H2L">
			<osc1
				type="sample"
				loopMode="1"
				reversed="0"
				timeStretchEnable="0"
				timeStretchAmount="0"
				fileName="SAMPLES/op1kits/acoustic_toy/17-noot.wav">
				<zone
					startSamplePos="0"
					endSamplePos="46670" />
			</osc1>
			<osc2
				type="sample"
				loopMode="0"
				reversed="0"
				timeStretchEnable="0"
				timeStretchAmount="0">
			</osc2>
			<lfo1 type="triangle" syncType="0" syncLevel="0" />
			<lfo2 type="triangle" />
			<unison num="1" detune="8" spread="0" />
			<delay
				pingPong="1"
				analog="0"
				syncType="0"
				syncLevel="7" />
			<sidechain
				syncType="0"
				syncLevel="6"
				attack="327244"
				release="936" />
			<audioCompressor
				attack="83886080"
				release="83886080"
				thresh="0"
				ratio="1073741824"
				compHPF="0" />
			<defaultParams
				arpeggiatorGate="0x00000000"
				ratchetProbability="0x80000000"
				ratchetAmount="0x80000000"
				sequenceLength="0x80000000"
				portamento="0x80000000"
				compressorShape="0xDC28F5B2"
				oscAVolume="0x7FFFFFFF"
				oscAPulseWidth="0x00000000"
				oscAWavetablePosition="0x00000000"
				oscBVolume="0x80000000"
				oscBPulseWidth="0x00000000"
				oscBWavetablePosition="0x00000000"
				noiseVolume="0x80000000"
				volume="0x4CCCCCA8"
				pan="0x00000000"
				waveFold="0x80000000"
				lpfFrequency="0x7FFFFFFF"
				lpfResonance="0x80000000"
				lpfMorph="0x80000000"
				hpfFrequency="0x80000000"
				hpfResonance="0x80000000"
				hpfMorph="0x80000000"
				lfo1Rate="0x1999997E"
				lfo2Rate="0x00000000"
				modulator1Amount="0x80000000"
				modulator1Feedback="0x80000000"
				modulator2Amount="0x80000000"
				modulator2Feedback="0x80000000"
				carrier1Feedback="0x80000000"
				carrier2Feedback="0x80000000"
				modFXRate="0x00000000"
				modFXDepth="0x00000000"
				delayRate="0x00000000"
				delayFeedback="0x80000000"
				reverbAmount="0x80000000"
				arpeggiatorRate="0x00000000"
				stutterRate="0x00000000"
				sampleRateReduction="0x80000000"
				bitCrush="0x80000000"
				modFXOffset="0x00000000"
				modFXFeedback="0x00000000"
				compressorThreshold="0x00000000">
				<envelope1
					attack="0x80000000"
					decay="0xE6666654"
					sustain="0x7FFFFFD2"
					release="0x80000000" />
				<envelope2
					attack="0xE6666654"
					decay="0xE6666654"
					sustain="0xFFFFFFE9"
					release="0xE6666654" />
				<patchCables>
					<patchCable
						source="velocity"
						destination="volume"
						amount="0x3FFFFFE8" />
					<patchCable
						source="aftertouch"
						destination="volume"
						amount="0x2A3D7094" />
					<patchCable
						source="y"
						destination="lpfFrequency"
						amount="0x19999990" />
				</patchCables>
				<equalizer
					bass="0x00000000"
					treble="0x00000000"
					bassFrequency="0x00000000"
					trebleFrequency="0x00000000" />
			</defaultParams>
			<arpeggiator
				arpMode="off"
				noteMode="up"
				octaveMode="up"
				mpeVelocity="off"
				numOctaves="2"
				rhythm="0"
				syncType="0"
				syncLevel="7" />
			<modKnobs>
				<modKnob controlsParam="pan" />
				<modKnob controlsParam="volumePostFX" />
				<modKnob controlsParam="lpfResonance" />
				<modKnob controlsParam="lpfFrequency" />
				<modKnob controlsParam="env1Release" />
				<modKnob controlsParam="env1Attack" />
				<modKnob controlsParam="delayFeedback" />
				<modKnob controlsParam="delayRate" />
				<modKnob controlsParam="reverbAmount" />
				<modKnob controlsParam="volumePostReverbSend" patchAmountFromSource="compressor" />
				<modKnob controlsParam="pitch" patchAmountFromSource="lfo1" />
				<modKnob controlsParam="lfo1Rate" />
				<modKnob controlsParam="pitch" />
				<modKnob controlsParam="stutterRate" />
				<modKnob controlsParam="bitcrushAmount" />
				<modKnob controlsParam="sampleRateReduction" />
			</modKnobs>
		</sound>
		<sound
			name="18-thirteen"
			path=""
			polyphonic="auto"
			voicePriority="1"
			mode="subtractive"
			lpfMode="24dB"
			hpfMode="HPLadder"
			modFXType="none"
			filterRoute="H2L">
			<osc1
				type="sample"
				loopMode="1"
				reversed="0"
				timeStretchEnable="0"
				timeStretchAmount="0"
				fileName="SAMPLES/op1kits/acoustic_toy/18-thirteen.wav">
				<zone
					startSamplePos="0"
					endSamplePos="3262" />
			</osc1>
			<osc2
				type="sample"
				loopMode="0"
				reversed="0"
				timeStretchEnable="0"
				timeStretchAmount="0">
			</osc2>
			<lfo1 type="triangle" syncType="0" syncLevel="0" />
			<lfo2 type="triangle" />
			<unison num="1" detune="8" spread="0" />
			<delay
				pingPong="1"
				analog="0"
				syncType="0"
				syncLevel="7" />
			<sidechain
				syncType="0"
				syncLevel="6"
				attack="327244"
				release="936" />
			<audioCompressor
				attack="83886080"
				release="83886080"
				thresh="0"
				ratio="1073741824"
				compHPF="0" />
			<defaultParams
				arpeggiatorGate="0x00000000"
				ratchetProbability="0x80000000"
				ratchetAmount="0x80000000"
				sequenceLength="0x80000000"
				portamento="0x80000000"
				compressorShape="0xDC28F5B2"
				oscAVolume="0x7FFFFFFF"
				oscAPulseWidth="0x00000000"
				oscAWavetablePosition="0x00000000"
				oscBVolume="0x80000000"
				oscBPulseWidth="0x00000000"
				oscBWavetablePosition="0x00000000"
				noiseVolume="0x80000000"
				volume="0x4CCCCCA8"
				pan="0x00000000"
				waveFold="0x80000000"
				lpfFrequency="0x7FFFFFFF"
				lpfResonance="0x80000000"
				lpfMorph="0x80000000"
				hpfFrequency="0x80000000"
				hpfResonance="0x80000000"
				hpfMorph="0x80000000"
				lfo1Rate="0x1999997E"
				lfo2Rate="0x00000000"
				modulator1Amount="0x80000000"
				modulator1Feedback="0x80000000"
				modulator2Amount="0x80000000"
				modulator2Feedback="0x80000000"
				carrier1Feedback="0x80000000"
				carrier2Feedback="0x80000000"
				modFXRate="0x00000000"
				modFXDepth="0x00000000"
				delayRate="0x00000000"
				delayFeedback="0x80000000"
				reverbAmount="0x80000000"
				arpeggiatorRate="0x00000000"
				stutterRate="0x00000000"
				sampleRateReduction="0x80000000"
				bitCrush="0x80000000"
				modFXOffset="0x00000000"
				modFXFeedback="0x00000000"
				compressorThreshold="0x00000000">
				<envelope1
					attack="0x80000000"
					decay="0xE6666654"
					sustain="0x7FFFFFD2"
					release="0x80000000" />
				<envelope2
					attack="0xE6666654"
					decay="0xE6666654"
					sustain="0xFFFFFFE9"
					release="0xE6666654" />
				<patchCables>
					<patchCable
						source="velocity"
						destination="volume"
						amount="0x3FFFFFE8" />
					<patchCable
						source="aftertouch"
						destination="volume"
						amount="0x2A3D7094" />
					<patchCable
						source="y"
						destination="lpfFrequency"
						amount="0x19999990" />
				</patchCables>
				<equalizer
					bass="0x00000000"
					treble="0x00000000"
					bassFrequency="0x00000000"
					trebleFrequency="0x00000000" />
			</defaultParams>
			<arpeggiator
				arpMode="off"
				noteMode="up"
				octaveMode="up"
				mpeVelocity="off"
				numOctaves="2"
				rhythm="0"
				syncType="0"
				syncLevel="7" />
			<modKnobs>
				<modKnob controlsParam="pan" />
				<modKnob controlsParam="volumePostFX" />
				<modKnob controlsParam="lpfResonance" />
				<modKnob controlsParam="lpfFrequency" />
				<modKnob controlsParam="env1Release" />
				<modKnob controlsParam="env1Attack" />
				<modKnob controlsParam="delayFeedback" />
				<modKnob controlsParam="delayRate" />
				<modKnob controlsParam="reverbAmount" />
				<modKnob controlsParam="volumePostReverbSend" patchAmountFromSource="compressor" />
				<modKnob controlsParam="pitch" patchAmountFromSource="lfo1" />
				<modKnob controlsParam="lfo1Rate" />
				<modKnob controlsParam="pitch" />
				<modKnob controlsParam="stutterRate" />
				<modKnob controlsParam="bitcrushAmount" />
				<modKnob controlsParam="sampleRateReduction" />
			</modKnobs>
		</sound>
		<sound
			name="19-fourteen"
			path=""
			polyphonic="auto"
			voicePriority="1"
			mode="subtractive"
			lpfMode="24dB"
			hpfMode="HPLadder"
			modFXType="none"
			filterRoute="H2L">
			<osc1
				type="sample"
				loopMode="1"
				reversed="0"
				timeStretchEnable="0"
				timeStretchAmount="0"
				fileName="SAMPLES/op1kits/acoustic_toy/19-fourteen.wav">
				<zone
					startSamplePos="0"
					endSamplePos="6695" />
			</osc1>
			<osc2
				type="sample"
				loopMode="0"
				reversed="0"
				timeStretchEnable="0"
				timeStretchAmount="0">
			</osc2>
			<lfo1 type="triangle" syncType="0" syncLevel="0" />
			<lfo2 type="triangle" />
			<unison num="1" detune="8" spread="0" />
			<delay
				pingPong="1"
				analog="0"
				syncType="0"
				syncLevel="7" />
			<sidechain
				syncType="0"
				syncLevel="6"
				attack="327244"
				release="936" />
			<audioCompressor
				attack="83886080"
				release="83886080"
				thresh="0"
				ratio="1073741824"
				compHPF="0" />
			<defaultParams
				arpeggiatorGate="0x00000000"
				ratchetProbability="0x80000000"
				ratchetAmount="0x80000000"
				sequenceLength="0x80000000"
				portamento="0x80000000"
				compressorShape="0xDC28F5B2"
				oscAVolume="0x7FFFFFFF"
				oscAPulseWidth="0x00000000"
				oscAWavetablePosition="0x00000000"
				oscBVolume="0x80000000"
				oscBPulseWidth="0x00000000"
				oscBWavetablePosition="0x00000000"
				noiseVolume="0x80000000"
				volume="0x4CCCCCA8"
				pan="0x00000000"
				waveFold="0x80000000"
				lpfFrequency="0x7FFFFFFF"
				lpfResonance="0x80000000"
				lpfMorph="0x80000000"
				hpfFrequency="0x80000000"
				hpfResonance="0x80000000"
				hpfMorph="0x80000000"
				lfo1Rate="0x1999997E"
				lfo2Rate="0x00000000"
				modulator1Amount="0x80000000"
				modulator1Feedback="0x80000000"
				modulator2Amount="0x80000000"
				modulator2Feedback="0x80000000"
				carrier1Feedback="0x80000000"
				carrier2Feedback="0x80000000"
				modFXRate="0x00000000"
				modFXDepth="0x00000000"
				delayRate="0x00000000"
				delayFeedback="0x80000000"
				reverbAmount="0x80000000"
				arpeggiatorRate="0x00000000"
				stutterRate="0x00000000"
				sampleRateReduction="0x80000000"
				bitCrush="0x80000000"
				modFXOffset="0x00000000"
				modFXFeedback="0x00000000"
				compressorThreshold="0x00000000">
				<envelope1
					attack="0x80000000"
					decay="0xE6666654"
					sustain="0x7FFFFFD2"
					release="0x80000000" />
				<envelope2
					attack="0xE6666654"
					decay="0xE6666654"
					sustain="0xFFFFFFE9"
					release="0xE6666654" />
				<patchCables>
					<patchCable
						source="velocity"
						destination="volume"
						amount="0x3FFFFFE8" />
					<patchCable
						source="aftertouch"
						destination="volume"
						amount="0x2A3D7094" />
					<patchCable
						source="y"
						destination="lpfFrequency"
						amount="0x19999990" />
				</patchCables>
				<equalizer
					bass="0x00000000"
					treble="0x00000000"
					bassFrequency="0x00000000"
					trebleFrequency="0x00000000" />
			</defaultParams>
			<arpeggiator
				arpMode="off"
				noteMode="up"
				octaveMode="up"
				mpeVelocity="off"
				numOctaves="2"
				rhythm="0"
				syncType="0"
				syncLevel="7" />
			<modKnobs>
				<modKnob controlsParam="pan" />
				<modKnob controlsParam="volumePostFX" />
				<modKnob controlsParam="lpfResonance" />
				<modKnob controlsParam="lpfFrequency" />
				<modKnob controlsParam="env1Release" />
				<modKnob controlsParam="env1Attack" />
				<modKnob controlsParam="delayFeedback" />
				<modKnob controlsParam="delayRate" />
				<modKnob controlsParam="reverbAmount" />
				<modKnob controlsParam="volumePostReverbSend" patchAmountFromSource="compressor" />
				<modKnob controlsParam="pitch" patchAmountFromSource="lfo1" />
				<modKnob controlsParam="lfo1Rate" />
				<modKnob controlsParam="pitch" />
				<modKnob controlsParam="stutterRate" />
				<modKnob controlsParam="bitcrushAmount" />
				<modKnob controlsParam="sampleRateReduction" />
			</modKnobs>
		</sound>
		<sound
			name="20-fx_1"
			path=""
			polyphonic="auto"
			voicePriority="1"
			mode="subtractive"
			lpfMode="24dB"
			hpfMode="HPLadder"
			modFXType="none"
			filterRoute="H2L">
			<osc1
				type="sample"
				loopMode="1"
				reversed="0"
				timeStretchEnable="0"
				timeStretchAmount="0"
				fileName="SAMPLES/op1kits/acoustic_toy/20-fx_1.wav">
				<zone
					startSamplePos="0"
					endSamplePos="5294" />
			</osc1>
			<osc2
				type="sample"
				loopMode="0"
				reversed="0"
				timeStretchEnable="0"
				timeStretchAmount="0">
			</osc2>
			<lfo1 type="triangle" syncType="0" syncLevel="0" />
			<lfo2 type="triangle" />
			<unison num="1" detune="8" spread="0" />
			<delay
				pingPong="1"
				analog="0"
				syncType="0"
				syncLevel="7" />
			<sidechain
				syncType="0"
				syncLevel="6"
				attack="327244"
				release="936" />
			<audioCompressor
				attack="83886080"
				release="83886080"
				thresh="0"
				ratio="1073741824"
				compHPF="0" />
			<defaultParams
				arpeggiatorGate="0x00000000"
				ratchetProbability="0x80000000"
				ratchetAmount="0x80000000"
				sequenceLength="0x80000000"
				portamento="0x80000000"
				compressorShape="0xDC28F5B2"
				oscAVolume="0x7FFFFFFF"
				oscAPulseWidth="0x00000000"
				oscAWavetablePosition="0x00000000"
				oscBVolume="0x80000000"
				oscBPulseWidth="0x00000000"
				oscBWavetablePosition="0x00000000"
				noiseVolume="0x80000000"
				volume="0x4CCCCCA8"
				pan="0x00000000"
				waveFold="0x80000000"
				lpfFrequency="0x7FFFFFFF"
				lpfResonance="0x80000000"
				lpfMorph="0x80000000"
				hpfFrequency="0x80000000"
				hpfResonance="0x80000000"
				hpfMorph="0x80000000"
				lfo1Rate="0x1999997E"
				lfo2Rate="0x00000000"
				modulator1Amount="0x80000000"
				modulator1Feedback="0x80000000"
				modulator2Amount="0x80000000"
				modulator2Feedback="0x80000000"
				carrier1Feedback="0x80000000"
				carrier2Feedback="0x80000000"
				modFXRate="0x00000000"
				modFXDepth="0x00000000"
				delayRate="0x00000000"
				delayFeedback="0x80000000"
				reverbAmount="0x80000000"
				arpeggiatorRate="0x00000000"
				stutterRate="0x00000000"
				sampleRateReduction="0x80000000"
				bitCrush="0x80000000"
				modFXOffset="0x00000000"
				modFXFeedback="0x00000000"
				compressorThreshold="0x00000000">
				<envelope1
					attack="0x80000000"
					decay="0xE6666654"
					sustain="0x7FFFFFD2"
					release="0x80000000" />
				<envelope2
					attack="0xE6666654"
					decay="0xE6666654"
					sustain="0xFFFFFFE9"
					release="0xE6666654" />
				<patchCables>
					<patchCable
						source="velocity"
						destination="volume"
						amount="0x3FFFFFE8" />
					<patchCable
						source="aftertouch"
						destination="volume"
						amount="0x2A3D7094" />
					<patchCable
						source="y"
						destination="lpfFrequency"
						amount="0x19999990" />
				</patchCables>
				<equalizer
					bass="0x00000000"
					treble="0x00000000"
					bassFrequency="0x00000000"
					trebleFrequency="0x00000000" />
			</defaultParams>
			<arpeggiator
				arpMode="off"
				noteMode="up"
				octaveMode="up"
				mpeVelocity="off"
				numOctaves="2"
				rhythm="0"
				syncType="0"
				syncLevel="7" />
			<modKnobs>
				<modKnob controlsParam="pan" />
				<modKnob controlsParam="volumePostFX" />
				<modKnob controlsParam="lpfResonance" />
				<modKnob controlsParam="lpfFrequency" />
				<modKnob controlsParam="env1Release" />
				<modKnob controlsParam="env1Attack" />
				<modKnob controlsParam="delayFeedback" />
				<modKnob controlsParam="delayRate" />
				<modKnob controlsParam="reverbAmount" />
				<modKnob controlsParam="volumePostReverbSend" patchAmountFromSource="compressor" />
				<modKnob controlsParam="pitch" patchAmountFromSource="lfo1" />
				<modKnob controlsParam="lfo1Rate" />
				<modKnob controlsParam="pitch" />
				<modKnob controlsParam="stutterRate" />
				<modKnob controlsParam="bitcrushAmount" />
				<modKnob controlsParam="sampleRateReduction" />
			</modKnobs>
		</sound>
		<sound
			name="21-fx_2"
			path=""
			polyphonic="auto"
			voicePriority="1"
			mode="subtractive"
			lpfMode="24dB"
			hpfMode="HPLadder"
			modFXType="none"
			filterRoute="H2L">
			<osc1
				type="sample"
				loopMode="1"
				reversed="0"
				timeStretchEnable="0"
				timeStretchAmount="0"
				fileName="SAMPLES/op1kits/acoustic_toy/21-fx_2.wav">
				<zone
					startSamplePos="0"
					endSamplePos="9593" />
			</osc1>
			<osc2
				type="sample"
				loopMode="0"
				reversed="0"
				timeStretchEnable="0"
				timeStretchAmount="0">
			</osc2>
			<lfo1 type="triangle" syncType="0" syncLevel="0" />
			<lfo2 type="triangle" />
			<unison num="1" detune="8" spread="0" />
			<delay
				pingPong="1"
				analog="0"
				syncType="0"
				syncLevel="7" />
			<sidechain
				syncType="0"
				syncLevel="6"
				attack="327244"
				release="936" />
			<audioCompressor
				attack="83886080"
				release="83886080"
				thresh="0"
				ratio="1073741824"
				compHPF="0" />
			<defaultParams
				arpeggiatorGate="0x00000000"
				ratchetProbability="0x80000000"
				ratchetAmount="0x80000000"
				sequenceLength="0x80000000"
				portamento="0x80000000"
				compressorShape="0xDC28F5B2"
				oscAVolume="0x7FFFFFFF"
				oscAPulseWidth="0x00000000"
				oscAWavetablePosition="0x00000000"
				oscBVolume="0x80000000"
				oscBPulseWidth="0x00000000"
				oscBWavetablePosition="0x00000000"
				noiseVolume="0x80000000"
				volume="0x4CCCCCA8"
				pan="0x00000000"
				waveFold="0x80000000"
				lpfFrequency="0x7FFFFFFF"
				lpfResonance="0x80000000"
				lpfMorph="0x80000000"
				hpfFrequency="0x80000000"
				hpfResonance="0x80000000"
				hpfMorph="0x80000000"
				lfo1Rate="0x1999997E"
				lfo2Rate="0x00000000"
				modulator1Amount="0x80000000"
				modulator1Feedback="0x80000000"
				modulator2Amount="0x80000000"
				modulator2Feedback="0x80000000"
				carrier1Feedback="0x80000000"
				carrier2Feedback="0x80000000"
				modFXRate="0x00000000"
				modFXDepth="0x00000000"
				delayRate="0x00000000"
				delayFeedback="0x80000000"
				reverbAmount="0x80000000"
				arpeggiatorRate="0x00000000"
				stutterRate="0x00000000"
				sampleRateReduction="0x80000000"
				bitCrush="0x80000000"
				modFXOffset="0x00000000"
				modFXFeedback="0x00000000"
				compressorThreshold="0x00000000">
				<envelope1
					attack="0x80000000"
					decay="0xE6666654"
					sustain="0x7FFFFFD2"
					release="0x80000000" />
				<envelope2
					attack="0xE6666654"
					decay="0xE6666654"
					sustain="0xFFFFFFE9"
					release="0xE6666654" />
				<patchCables>
					<patchCable
						source="velocity"
						destination="volume"
						amount="0x3FFFFFE8" />
					<patchCable
						source="aftertouch"
						destination="volume"
						amount="0x2A3D7094" />
					<patchCable
						source="y"
						destination="lpfFrequency"
						amount="0x19999990" />
				</patchCables>
				<equalizer
					bass="0x00000000"
					treble="0x00000000"
					bassFrequency="0x00000000"
					trebleFrequency="0x00000000" />
			</defaultParams>
			<arpeggiator
				arpMode="off"
				noteMode="up"
				octaveMode="up"
				mpeVelocity="off"
				numOctaves="2"
				rhythm="0"
				syncType="0"
				syncLevel="7" />
			<modKnobs>
				<modKnob controlsParam="pan" />
				<modKnob controlsParam="volumePostFX" />
				<modKnob controlsParam="lpfResonance" />
				<modKnob controlsParam="lpfFrequency" />
				<modKnob controlsParam="env1Release" />
				<modKnob controlsParam="env1Attack" />
				<modKnob controlsParam="delayFeedback" />
				<modKnob controlsParam="delayRate" />
				<modKnob controlsParam="reverbAmount" />
				<modKnob controlsParam="volumePostReverbSend" patchAmountFromSource="compressor" />
				<modKnob controlsParam="pitch" patchAmountFromSource="lfo1" />
				<modKnob controlsParam="lfo1Rate" />
				<modKnob controlsParam="pitch" />
				<modKnob controlsParam="stutterRate" />
				<modKnob controlsParam="bitcrushAmount" />
				<modKnob controlsParam="sampleRateReduction" />
			</modKnobs>
		</sound>
		<sound
			name="22-fx_3"
			path=""
			polyphonic="auto"
			voicePriority="1"
			mode="subtractive"
			lpfMode="24dB"
			hpfMode="HPLadder"
			modFXType="none"
			filterRoute="H2L">
			<osc1
				type="sample"
				loopMode="1"
				reversed="0"
				timeStretchEnable="0"
				timeStretchAmount="0"
				fileName="SAMPLES/op1kits/acoustic_toy/22-fx_3.wav">
				<zone
					startSamplePos="0"
					endSamplePos="10538" />
			</osc1>
			<osc2
				type="sample"
				loopMode="0"
				reversed="0"
				timeStretchEnable="0"
				timeStretchAmount="0">
			</osc2>
			<lfo1 type="triangle" syncType="0" syncLevel="0" />
			<lfo2 type="triangle" />
			<unison num="1" detune="8" spread="0" />
			<delay
				pingPong="1"
				analog="0"
				syncType="0"
				syncLevel="7" />
			<sidechain
				syncType="0"
				syncLevel="6"
				attack="327244"
				release="936" />
			<audioCompressor
				attack="83886080"
				release="83886080"
				thresh="0"
				ratio="1073741824"
				compHPF="0" />
			<defaultParams
				arpeggiatorGate="0x00000000"
				ratchetProbability="0x80000000"
				ratchetAmount="0x80000000"
				sequenceLength="0x80000000"
				portamento="0x80000000"
				compressorShape="0xDC28F5B2"
				oscAVolume="0x7FFFFFFF"
				oscAPulseWidth="0x00000000"
				oscAWavetablePosition="0x00000000"
				oscBVolume="0x80000000"
				oscBPulseWidth="0x00000000"
				oscBWavetablePosition="0x00000000"
				noiseVolume="0x80000000"
				volume="0x4CCCCCA8"
				pan="0x00000000"
				waveFold="0x80000000"
				lpfFrequency="0x7FFFFFFF"
				lpfResonance="0x80000000"
				lpfMorph="0x80000000"
				hpfFrequency="0x80000000"
				hpfResonance="0x80000000"
				hpfMorph="0x80000000"
				lfo1Rate="0x1999997E"
				lfo2Rate="0x00000000"
				modulator1Amount="0x80000000"
				modulator1Feedback="0x80000000"
				modulator2Amount="0x80000000"
				modulator2Feedback="0x80000000"
				carrier1Feedback="0x80000000"
				carrier2Feedback="0x80000000"
				modFXRate="0x00000000"
				modFXDepth="0x00000000"
				delayRate="0x00000000"
				delayFeedback="0x80000000"
				reverbAmount="0x80000000"
				arpeggiatorRate="0x00000000"
				stutterRate="0x00000000"
				sampleRateReduction="0x80000000"
				bitCrush="0x80000000"
				modFXOffset="0x00000000"
				modFXFeedback="0x00000000"
				compressorThreshold="0x00000000">
				<envelope1
					attack="0x80000000"
					decay="0xE6666654"
					sustain="0x7FFFFFD2"
					release="0x80000000" />
				<envelope2
					attack="0xE6666654"
					decay="0xE6666654"
					sustain="0xFFFFFFE9"
					release="0xE6666654" />
				<patchCables>
					<patchCable
						source="velocity"
						destination="volume"
						amount="0x3FFFFFE8" />
					<patchCable
						source="aftertouch"
						destination="volume"
						amount="0x2A3D7094" />
					<patchCable
						source="y"
						destination="lpfFrequency"
						amount="0x19999990" />
				</patchCables>
				<equalizer
					bass="0x00000000"
					treble="0x00000000"
					bassFrequency="0x00000000"
					trebleFrequency="0x00000000" />
			</defaultParams>
			<arpeggiator
				arpMode="off"
				noteMode="up"
				octaveMode="up"
				mpeVelocity="off"
				numOctaves="2"
				rhythm="0"
				syncType="0"
				syncLevel="7" />
			<modKnobs>
				<modKnob controlsParam="pan" />
				<modKnob controlsParam="volumePostFX" />
				<modKnob controlsParam="lpfResonance" />
				<modKnob controlsParam="lpfFrequency" />
				<modKnob controlsParam="env1Release" />
				<modKnob controlsParam="env1Attack" />
				<modKnob controlsParam="delayFeedback" />
				<modKnob controlsParam="delayRate" />
				<modKnob controlsParam="reverbAmount" />
				<modKnob controlsParam="volumePostReverbSend" patchAmountFromSource="compressor" />
				<modKnob controlsParam="pitch" patchAmountFromSource="lfo1" />
				<modKnob controlsParam="lfo1Rate" />
				<modKnob controlsParam="pitch" />
				<modKnob controlsParam="stutterRate" />
				<modKnob controlsParam="bitcrushAmount" />
				<modKnob controlsParam="sampleRateReduction" />
			</modKnobs>
		</sound>
		<sound
			name="23-fx_4"
			path=""
			polyphonic="auto"
			voicePriority="1"
			mode="subtractive"
			lpfMode="24dB"
			hpfMode="HPLadder"
			modFXType="none"
			filterRoute="H2L">
			<osc1
				type="sample"
				loopMode="1"
				reversed="0"
				timeStretchEnable="0"
				timeStretchAmount="0"
				fileName="SAMPLES/op1kits/acoustic_toy/23-fx_4.wav">
				<zone
					startSamplePos="0"
					endSamplePos="7161" />
			</osc1>
			<osc2
				type="sample"
				loopMode="0"
				reversed="0"
				timeStretchEnable="0"
				timeStretchAmount="0">
			</osc2>
			<lfo1 type="triangle" syncType="0" syncLevel="0" />
			<lfo2 type="triangle" />
			<unison num="1" detune="8" spread="0" />
			<delay
				pingPong="1"
				analog="0"
				syncType="0"
				syncLevel="7" />
			<sidechain
				syncType="0"
				syncLevel="6"
				attack="327244"
				release="936" />
			<audioCompressor
				attack="83886080"
				release="83886080"
				thresh="0"
				ratio="1073741824"
				compHPF="0" />
			<defaultParams
				arpeggiatorGate="0x00000000"
				ratchetProbability="0x80000000"
				ratchetAmount="0x80000000"
				sequenceLength="0x80000000"
				portamento="0x80000000"
				compressorShape="0xDC28F5B2"
				oscAVolume="0x7FFFFFFF"
				oscAPulseWidth="0x00000000"
				oscAWavetablePosition="0x00000000"
				oscBVolume="0x80000000"
				oscBPulseWidth="0x00000000"
				oscBWavetablePosition="0x00000000"
				noiseVolume="0x80000000"
				volume="0x4CCCCCA8"
				pan="0x00000000"
				waveFold="0x80000000"
				lpfFrequency="0x7FFFFFFF"
				lpfResonance="0x80000000"
				lpfMorph="0x80000000"
				hpfFrequency="0x80000000"
				hpfResonance="0x80000000"
				hpfMorph="0x80000000"
				lfo1Rate="0x1999997E"
				lfo2Rate="0x00000000"
				modulator1Amount="0x80000000"
				modulator1Feedback="0x80000000"
				modulator2Amount="0x80000000"
				modulator2Feedback="0x80000000"
				carrier1Feedback="0x80000000"
				carrier2Feedback="0x80000000"
				modFXRate="0x00000000"
				modFXDepth="0x00000000"
				delayRate="0x00000000"
				delayFeedback="0x80000000"
				reverbAmount="0x80000000"
				arpeggiatorRate="0x00000000"
				stutterRate="0x00000000"
				sampleRateReduction="0x80000000"
				bitCrush="0x80000000"
				modFXOffset="0x00000000"
				modFXFeedback="0x00000000"
				compressorThreshold="0x00000000">
				<envelope1
					attack="0x80000000"
					decay="0xE6666654"
					sustain="0x7FFFFFD2"
					release="0x80000000" />
				<envelope2
					attack="0xE6666654"
					decay="0xE6666654"
					sustain="0xFFFFFFE9"
					release="0xE6666654" />
				<patchCables>
					<patchCable
						source="velocity"
						destination="volume"
						amount="0x3FFFFFE8" />
					<patchCable
						source="aftertouch"
						destination="volume"
						amount="0x2A3D7094" />
					<patchCable
						source="y"
						destination="lpfFrequency"
						amount="0x19999990" />
				</patchCables>
				<equalizer
					bass="0x00000000"
					treble="0x00000000"
					bassFrequency="0x00000000"
					trebleFrequency="0x00000000" />
			</defaultParams>
			<arpeggiator
				arpMode="off"
				noteMode="up"
				octaveMode="up"
				mpeVelocity="off"
				numOctaves="2"
				rhythm="0"
				syncType="0"
				syncLevel="7" />
			<modKnobs>
				<modKnob controlsParam="pan" />
				<modKnob controlsParam="volumePostFX" />
				<modKnob controlsParam="lpfResonance" />
				<modKnob controlsParam="lpfFrequency" />
				<modKnob controlsParam="env1Release" />
				<modKnob controlsParam="env1Attack" />
				<modKnob controlsParam="delayFeedback" />
				<modKnob controlsParam="delayRate" />
				<modKnob controlsParam="reverbAmount" />
				<modKnob controlsParam="volumePostReverbSend" patchAmountFromSource="compressor" />
				<modKnob controlsParam="pitch" patchAmountFromSource="lfo1" />
				<modKnob controlsParam="lfo1Rate" />
				<modKnob controlsParam="pitch" />
				<modKnob controlsParam="stutterRate" />
				<modKnob controlsParam="bitcrushAmount" />
				<modKnob controlsParam="sampleRateReduction" />
			</modKnobs>
		</sound>
		<sound
			name="24-fx_5"
			path=""
			polyphonic="auto"
			voicePriority="1"
			mode="subtractive"
			lpfMode="24dB"
			hpfMode="HPLadder"
			modFXType="none"
			filterRoute="H2L">
			<osc1
				type="sample"
				loopMode="1"
				reversed="0"
				timeStretchEnable="0"
				timeStretchAmount="0"
				fileName="SAMPLES/op1kits/acoustic_toy/24-fx_5.wav">
				<zone
					startSamplePos="0"
					endSamplePos="8829" />
			</osc1>
			<osc2
				type="sample"
				loopMode="0"
				reversed="0"
				timeStretchEnable="0"
				timeStretchAmount="0">
			</osc2>
			<lfo1 type="triangle" syncType="0" syncLevel="0" />
			<lfo2 type="triangle" />
			<unison num="1" detune="8" spread="0" />
			<delay
				pingPong="1"
				analog="0"
				syncType="0"
				syncLevel="7" />
			<sidechain
				syncType="0"
				syncLevel="6"
				attack="327244"
				release="936" />
			<audioCompressor
				attack="83886080"
				release="83886080"
				thresh="0"
				ratio="1073741824"
				compHPF="0" />
			<defaultParams
				arpeggiatorGate="0x00000000"
				ratchetProbability="0x80000000"
				ratchetAmount="0x80000000"
				sequenceLength="0x80000000"
				portamento="0x80000000"
				compressorShape="0xDC28F5B2"
				oscAVolume="0x7FFFFFFF"
				oscAPulseWidth="0x00000000"
				oscAWavetablePosition="0x00000000"
				oscBVolume="0x80000000"
				oscBPulseWidth="0x00000000"
				oscBWavetablePosition="0x00000000"
				noiseVolume="0x80000000"
				volume="0x4CCCCCA8"
				pan="0x00000000"
				waveFold="0x80000000"
				lpfFrequency="0x7FFFFFFF"
				lpfResonance="0x80000000"
				lpfMorph="0x80000000"
				hpfFrequency="0x80000000"
				hpfResonance="0x80000000"
				hpfMorph="0x80000000"
				lfo1Rate="0x1999997E"
				lfo2Rate="0x00000000"
				modulator1Amount="0x80000000"
				modulator1Feedback="0x80000000"
				modulator2Amount="0x80000000"
				modulator2Feedback="0x80000000"
				carrier1Feedback="0x80000000"
				carrier2Feedback="0x80000000"
				modFXRate="0x00000000"
				modFXDepth="0x00000000"
				delayRate="0x00000000"
				delayFeedback="0x80000000"
				reverbAmount="0x80000000"
				arpeggiatorRate="0x00000000"
				stutterRate="0x00000000"
				sampleRateReduction="0x80000000"
				bitCrush="0x80000000"
				modFXOffset="0x00000000"
				modFXFeedback="0x00000000"
				compressorThreshold="0x00000000">
				<envelope1
					attack="0x80000000"
					decay="0xE6666654"
					sustain="0x7FFFFFD2"
					release="0x80000000" />
				<envelope2
					attack="0xE6666654"
					decay="0xE6666654"
					sustain="0xFFFFFFE9"
					release="0xE6666654" />
				<patchCables>
					<patchCable
						source="velocity"
						destination="volume"
						amount="0x3FFFFFE8" />
					<patchCable
						source="aftertouch"
						destination="volume"
						amount="0x2A3D7094" />
					<patchCable
						source="y"
						destination="lpfFrequency"
						amount="0x19999990" />
				</patchCables>
				<equalizer
					bass="0x00000000"
					treble="0x00000000"
					bassFrequency="0x00000000"
					trebleFrequency="0x00000000" />
			</defaultParams>
			<arpeggiator
				arpMode="off"
				noteMode="up"
				octaveMode="up"
				mpeVelocity="off"
				numOctaves="2"
				rhythm="0"
				syncType="0"
				syncLevel="7" />
			<modKnobs>
				<modKnob controlsParam="pan" />
				<modKnob controlsParam="volumePostFX" />
				<modKnob controlsParam="lpfResonance" />
				<modKnob controlsParam="lpfFrequency" />
				<modKnob controlsParam="env1Release" />
				<modKnob controlsParam="env1Attack" />
				<modKnob controlsParam="delayFeedback" />
				<modKnob controlsParam="delayRate" />
				<modKnob controlsParam="reverbAmount" />
				<modKnob controlsParam="volumePostReverbSend" patchAmountFromSource="compressor" />
				<modKnob controlsParam="pitch" patchAmountFromSource="lfo1" />
				<modKnob controlsParam="lfo1Rate" />
				<modKnob controlsParam="pitch" />
				<modKnob controlsParam="stutterRate" />
				<modKnob controlsParam="bitcrushAmount" />
				<modKnob controlsParam="sampleRateReduction" />
			</modKnobs>
		</sound>
	</soundSources>
	<selectedDrumIndex>2</selectedDrumIndex>
</kit>
